<?xml version="1.0" encoding="UTF-8"?>
<java version="1.8.0_331" class="java.beans.XMLDecoder">
 <object class="net.sf.jaxodraw.graph.JaxoSaveGraph" id="JaxoSaveGraph0">
  <void property="jaxoDrawVersion">
   <string>2.1-0</string>
  </void>
  <void property="objectList">
   <void method="add">
    <object class="net.sf.jaxodraw.object.text.JaxoLatexText" id="JaxoLatexText0">
     <void property="allign">
      <int>2</int>
     </void>
     <void property="color">
      <object class="java.awt.Color" id="Color0">
       <int>0</int>
       <int>0</int>
       <int>0</int>
       <int>255</int>
      </object>
     </void>
     <void property="latexTextSize">
      <int>9</int>
     </void>
     <void id="PointArray0" property="points">
      <void id="Point0" index="0">
       <void class="java.awt.Point" method="getField">
        <string>x</string>
        <void method="set">
         <object idref="Point0"/>
         <int>592</int>
        </void>
       </void>
       <void class="java.awt.Point" method="getField">
        <string>y</string>
        <void method="set">
         <object idref="Point0"/>
         <int>325</int>
        </void>
       </void>
      </void>
     </void>
     <void property="points">
      <object idref="PointArray0"/>
     </void>
     <void property="textString">
      <string>+</string>
     </void>
    </object>
   </void>
   <void method="add">
    <object class="net.sf.jaxodraw.object.text.JaxoLatexText" id="JaxoLatexText1">
     <void property="allign">
      <int>2</int>
     </void>
     <void property="color">
      <object idref="Color0"/>
     </void>
     <void property="latexTextSize">
      <int>9</int>
     </void>
     <void id="PointArray1" property="points">
      <void id="Point1" index="0">
       <void class="java.awt.Point" method="getField">
        <string>x</string>
        <void method="set">
         <object idref="Point1"/>
         <int>444</int>
        </void>
       </void>
       <void class="java.awt.Point" method="getField">
        <string>y</string>
        <void method="set">
         <object idref="Point1"/>
         <int>256</int>
        </void>
       </void>
      </void>
     </void>
     <void property="points">
      <object idref="PointArray1"/>
     </void>
     <void property="textString">
      <string>\gamma_1^1</string>
     </void>
    </object>
   </void>
   <void method="add">
    <object class="net.sf.jaxodraw.object.text.JaxoLatexText" id="JaxoLatexText2">
     <void property="allign">
      <int>2</int>
     </void>
     <void property="color">
      <object idref="Color0"/>
     </void>
     <void property="latexTextSize">
      <int>9</int>
     </void>
     <void id="PointArray2" property="points">
      <void id="Point2" index="0">
       <void class="java.awt.Point" method="getField">
        <string>x</string>
        <void method="set">
         <object idref="Point2"/>
         <int>586</int>
        </void>
       </void>
       <void class="java.awt.Point" method="getField">
        <string>y</string>
        <void method="set">
         <object idref="Point2"/>
         <int>561</int>
        </void>
       </void>
      </void>
     </void>
     <void property="points">
      <object idref="PointArray2"/>
     </void>
     <void property="textString">
      <string>+</string>
     </void>
    </object>
   </void>
   <void method="add">
    <object class="net.sf.jaxodraw.object.group.JaxoGroup" id="JaxoGroup0">
     <void property="objectList">
      <void method="add">
       <object class="net.sf.jaxodraw.object.line.JaxoFLine" id="JaxoFLine0">
        <void property="DLSeparation">
         <float>2.0</float>
        </void>
        <void property="amp">
         <int>15</int>
        </void>
        <void property="arrowPosition">
         <float>0.5</float>
        </void>
        <void property="color">
         <object idref="Color0"/>
        </void>
        <void property="paintArrow">
         <boolean>true</boolean>
        </void>
        <void id="PointArray3" property="points">
         <void id="Point3" index="0">
          <void class="java.awt.Point" method="getField">
           <string>x</string>
           <void method="set">
            <object idref="Point3"/>
            <int>669</int>
           </void>
          </void>
          <void class="java.awt.Point" method="getField">
           <string>y</string>
           <void method="set">
            <object idref="Point3"/>
            <int>386</int>
           </void>
          </void>
         </void>
         <void id="Point4" index="1">
          <void class="java.awt.Point" method="getField">
           <string>x</string>
           <void method="set">
            <object idref="Point4"/>
            <int>700</int>
           </void>
          </void>
          <void class="java.awt.Point" method="getField">
           <string>y</string>
           <void method="set">
            <object idref="Point4"/>
            <int>320</int>
           </void>
          </void>
         </void>
        </void>
        <void property="points">
         <object idref="PointArray3"/>
        </void>
        <void property="strokeWidth">
         <float>1.0</float>
        </void>
       </object>
      </void>
      <void method="add">
       <object class="net.sf.jaxodraw.object.line.JaxoFLine" id="JaxoFLine1">
        <void property="DLSeparation">
         <float>2.0</float>
        </void>
        <void property="amp">
         <int>15</int>
        </void>
        <void property="arrowPosition">
         <float>0.5</float>
        </void>
        <void property="color">
         <object idref="Color0"/>
        </void>
        <void property="paintArrow">
         <boolean>true</boolean>
        </void>
        <void id="PointArray4" property="points">
         <void id="Point5" index="0">
          <void class="java.awt.Point" method="getField">
           <string>x</string>
           <void method="set">
            <object idref="Point5"/>
            <int>700</int>
           </void>
          </void>
          <void class="java.awt.Point" method="getField">
           <string>y</string>
           <void method="set">
            <object idref="Point5"/>
            <int>320</int>
           </void>
          </void>
         </void>
         <void id="Point6" index="1">
          <void class="java.awt.Point" method="getField">
           <string>x</string>
           <void method="set">
            <object idref="Point6"/>
            <int>669</int>
           </void>
          </void>
          <void class="java.awt.Point" method="getField">
           <string>y</string>
           <void method="set">
            <object idref="Point6"/>
            <int>257</int>
           </void>
          </void>
         </void>
        </void>
        <void property="points">
         <object idref="PointArray4"/>
        </void>
        <void property="strokeWidth">
         <float>1.0</float>
        </void>
       </object>
      </void>
      <void method="add">
       <object class="net.sf.jaxodraw.object.line.JaxoFLine" id="JaxoFLine2">
        <void property="DLSeparation">
         <float>2.0</float>
        </void>
        <void property="amp">
         <int>15</int>
        </void>
        <void property="arrowPosition">
         <float>0.5</float>
        </void>
        <void property="color">
         <object idref="Color0"/>
        </void>
        <void property="paintArrow">
         <boolean>true</boolean>
        </void>
        <void id="PointArray5" property="points">
         <void id="Point7" index="0">
          <void class="java.awt.Point" method="getField">
           <string>x</string>
           <void method="set">
            <object idref="Point7"/>
            <int>843</int>
           </void>
          </void>
          <void class="java.awt.Point" method="getField">
           <string>y</string>
           <void method="set">
            <object idref="Point7"/>
            <int>384</int>
           </void>
          </void>
         </void>
         <void id="Point8" index="1">
          <void class="java.awt.Point" method="getField">
           <string>x</string>
           <void method="set">
            <object idref="Point8"/>
            <int>813</int>
           </void>
          </void>
          <void class="java.awt.Point" method="getField">
           <string>y</string>
           <void method="set">
            <object idref="Point8"/>
            <int>318</int>
           </void>
          </void>
         </void>
        </void>
        <void property="points">
         <object idref="PointArray5"/>
        </void>
        <void property="strokeWidth">
         <float>1.0</float>
        </void>
       </object>
      </void>
      <void method="add">
       <object class="net.sf.jaxodraw.object.line.JaxoFLine" id="JaxoFLine3">
        <void property="DLSeparation">
         <float>2.0</float>
        </void>
        <void property="amp">
         <int>15</int>
        </void>
        <void property="arrowPosition">
         <float>0.5</float>
        </void>
        <void property="color">
         <object idref="Color0"/>
        </void>
        <void property="paintArrow">
         <boolean>true</boolean>
        </void>
        <void id="PointArray6" property="points">
         <void id="Point9" index="0">
          <void class="java.awt.Point" method="getField">
           <string>x</string>
           <void method="set">
            <object idref="Point9"/>
            <int>814</int>
           </void>
          </void>
          <void class="java.awt.Point" method="getField">
           <string>y</string>
           <void method="set">
            <object idref="Point9"/>
            <int>318</int>
           </void>
          </void>
         </void>
         <void id="Point10" index="1">
          <void class="java.awt.Point" method="getField">
           <string>x</string>
           <void method="set">
            <object idref="Point10"/>
            <int>845</int>
           </void>
          </void>
          <void class="java.awt.Point" method="getField">
           <string>y</string>
           <void method="set">
            <object idref="Point10"/>
            <int>255</int>
           </void>
          </void>
         </void>
        </void>
        <void property="points">
         <object idref="PointArray6"/>
        </void>
        <void property="strokeWidth">
         <float>1.0</float>
        </void>
       </object>
      </void>
      <void method="add">
       <object class="net.sf.jaxodraw.object.text.JaxoLatexText" id="JaxoLatexText3">
        <void property="allign">
         <int>2</int>
        </void>
        <void property="color">
         <object idref="Color0"/>
        </void>
        <void property="latexTextSize">
         <int>9</int>
        </void>
        <void id="PointArray7" property="points">
         <void id="Point11" index="0">
          <void class="java.awt.Point" method="getField">
           <string>x</string>
           <void method="set">
            <object idref="Point11"/>
            <int>716</int>
           </void>
          </void>
          <void class="java.awt.Point" method="getField">
           <string>y</string>
           <void method="set">
            <object idref="Point11"/>
            <int>272</int>
           </void>
          </void>
         </void>
        </void>
        <void property="points">
         <object idref="PointArray7"/>
        </void>
        <void property="textString">
         <string>(z_1+f_1\Pi_0^*) R_q</string>
        </void>
       </object>
      </void>
      <void method="add">
       <object class="net.sf.jaxodraw.object.line.JaxoPLine" id="JaxoPLine0">
        <void property="DLSeparation">
         <float>2.0</float>
        </void>
        <void property="amp">
         <int>15</int>
        </void>
        <void property="color">
         <object idref="Color0"/>
        </void>
        <void id="PointArray8" property="points">
         <void id="Point12" index="0">
          <void class="java.awt.Point" method="getField">
           <string>x</string>
           <void method="set">
            <object idref="Point12"/>
            <int>701</int>
           </void>
          </void>
          <void class="java.awt.Point" method="getField">
           <string>y</string>
           <void method="set">
            <object idref="Point12"/>
            <int>320</int>
           </void>
          </void>
         </void>
         <void id="Point13" index="1">
          <void class="java.awt.Point" method="getField">
           <string>x</string>
           <void method="set">
            <object idref="Point13"/>
            <int>812</int>
           </void>
          </void>
          <void class="java.awt.Point" method="getField">
           <string>y</string>
           <void method="set">
            <object idref="Point13"/>
            <int>319</int>
           </void>
          </void>
         </void>
        </void>
        <void property="points">
         <object idref="PointArray8"/>
        </void>
        <void property="strokeWidth">
         <float>1.0</float>
        </void>
        <void property="wiggles">
         <int>6</int>
        </void>
       </object>
      </void>
      <void method="add">
       <object class="net.sf.jaxodraw.object.vertex.JaxoVertexT2" id="JaxoVertexT20">
        <void property="color">
         <object idref="Color0"/>
        </void>
        <void property="fillColor">
         <object class="java.awt.Color" id="Color1">
          <int>255</int>
          <int>255</int>
          <int>255</int>
          <int>255</int>
         </object>
        </void>
        <void id="PointArray9" property="points">
         <void id="Point14" index="0">
          <void class="java.awt.Point" method="getField">
           <string>x</string>
           <void method="set">
            <object idref="Point14"/>
            <int>755</int>
           </void>
          </void>
          <void class="java.awt.Point" method="getField">
           <string>y</string>
           <void method="set">
            <object idref="Point14"/>
            <int>320</int>
           </void>
          </void>
         </void>
         <void id="Point15" index="1">
          <void class="java.awt.Point" method="getField">
           <string>x</string>
           <void method="set">
            <object idref="Point15"/>
            <int>763</int>
           </void>
          </void>
          <void class="java.awt.Point" method="getField">
           <string>y</string>
           <void method="set">
            <object idref="Point15"/>
            <int>328</int>
           </void>
          </void>
         </void>
        </void>
        <void property="points">
         <object idref="PointArray9"/>
        </void>
        <void property="strokeWidth">
         <float>1.0</float>
        </void>
       </object>
      </void>
     </void>
     <void id="PointArray10" property="points">
      <void id="Point16" index="0">
       <void class="java.awt.Point" method="getField">
        <string>x</string>
        <void method="set">
         <object idref="Point16"/>
         <int>668</int>
        </void>
       </void>
       <void class="java.awt.Point" method="getField">
        <string>y</string>
        <void method="set">
         <object idref="Point16"/>
         <int>251</int>
        </void>
       </void>
      </void>
      <void id="Point17" index="1">
       <void class="java.awt.Point" method="getField">
        <string>x</string>
        <void method="set">
         <object idref="Point17"/>
         <int>846</int>
        </void>
       </void>
       <void class="java.awt.Point" method="getField">
        <string>y</string>
        <void method="set">
         <object idref="Point17"/>
         <int>387</int>
        </void>
       </void>
      </void>
     </void>
     <void property="points">
      <object idref="PointArray10"/>
     </void>
    </object>
   </void>
   <void method="add">
    <object class="net.sf.jaxodraw.object.line.JaxoFLine" id="JaxoFLine4">
     <void property="DLSeparation">
      <float>2.0</float>
     </void>
     <void property="amp">
      <int>15</int>
     </void>
     <void property="arrowPosition">
      <float>0.5</float>
     </void>
     <void property="color">
      <object idref="Color0"/>
     </void>
     <void property="paintArrow">
      <boolean>true</boolean>
     </void>
     <void id="PointArray11" property="points">
      <void id="Point18" index="0">
       <void class="java.awt.Point" method="getField">
        <string>x</string>
        <void method="set">
         <object idref="Point18"/>
         <int>664</int>
        </void>
       </void>
       <void class="java.awt.Point" method="getField">
        <string>y</string>
        <void method="set">
         <object idref="Point18"/>
         <int>617</int>
        </void>
       </void>
      </void>
      <void id="Point19" index="1">
       <void class="java.awt.Point" method="getField">
        <string>x</string>
        <void method="set">
         <object idref="Point19"/>
         <int>695</int>
        </void>
       </void>
       <void class="java.awt.Point" method="getField">
        <string>y</string>
        <void method="set">
         <object idref="Point19"/>
         <int>551</int>
        </void>
       </void>
      </void>
     </void>
     <void property="points">
      <object idref="PointArray11"/>
     </void>
     <void property="strokeWidth">
      <float>1.0</float>
     </void>
    </object>
   </void>
   <void method="add">
    <object class="net.sf.jaxodraw.object.line.JaxoFLine" id="JaxoFLine5">
     <void property="DLSeparation">
      <float>2.0</float>
     </void>
     <void property="amp">
      <int>15</int>
     </void>
     <void property="arrowPosition">
      <float>0.5</float>
     </void>
     <void property="color">
      <object idref="Color0"/>
     </void>
     <void property="paintArrow">
      <boolean>true</boolean>
     </void>
     <void id="PointArray12" property="points">
      <void id="Point20" index="0">
       <void class="java.awt.Point" method="getField">
        <string>x</string>
        <void method="set">
         <object idref="Point20"/>
         <int>695</int>
        </void>
       </void>
       <void class="java.awt.Point" method="getField">
        <string>y</string>
        <void method="set">
         <object idref="Point20"/>
         <int>551</int>
        </void>
       </void>
      </void>
      <void id="Point21" index="1">
       <void class="java.awt.Point" method="getField">
        <string>x</string>
        <void method="set">
         <object idref="Point21"/>
         <int>664</int>
        </void>
       </void>
       <void class="java.awt.Point" method="getField">
        <string>y</string>
        <void method="set">
         <object idref="Point21"/>
         <int>488</int>
        </void>
       </void>
      </void>
     </void>
     <void property="points">
      <object idref="PointArray12"/>
     </void>
     <void property="strokeWidth">
      <float>1.0</float>
     </void>
    </object>
   </void>
   <void method="add">
    <object class="net.sf.jaxodraw.object.line.JaxoFLine" id="JaxoFLine6">
     <void property="DLSeparation">
      <float>2.0</float>
     </void>
     <void property="amp">
      <int>15</int>
     </void>
     <void property="arrowPosition">
      <float>0.5</float>
     </void>
     <void property="color">
      <object idref="Color0"/>
     </void>
     <void property="paintArrow">
      <boolean>true</boolean>
     </void>
     <void id="PointArray13" property="points">
      <void id="Point22" index="0">
       <void class="java.awt.Point" method="getField">
        <string>x</string>
        <void method="set">
         <object idref="Point22"/>
         <int>838</int>
        </void>
       </void>
       <void class="java.awt.Point" method="getField">
        <string>y</string>
        <void method="set">
         <object idref="Point22"/>
         <int>615</int>
        </void>
       </void>
      </void>
      <void id="Point23" index="1">
       <void class="java.awt.Point" method="getField">
        <string>x</string>
        <void method="set">
         <object idref="Point23"/>
         <int>808</int>
        </void>
       </void>
       <void class="java.awt.Point" method="getField">
        <string>y</string>
        <void method="set">
         <object idref="Point23"/>
         <int>549</int>
        </void>
       </void>
      </void>
     </void>
     <void property="points">
      <object idref="PointArray13"/>
     </void>
     <void property="strokeWidth">
      <float>1.0</float>
     </void>
    </object>
   </void>
   <void method="add">
    <object class="net.sf.jaxodraw.object.line.JaxoFLine" id="JaxoFLine7">
     <void property="DLSeparation">
      <float>2.0</float>
     </void>
     <void property="amp">
      <int>15</int>
     </void>
     <void property="arrowPosition">
      <float>0.5</float>
     </void>
     <void property="color">
      <object idref="Color0"/>
     </void>
     <void property="paintArrow">
      <boolean>true</boolean>
     </void>
     <void id="PointArray14" property="points">
      <void id="Point24" index="0">
       <void class="java.awt.Point" method="getField">
        <string>x</string>
        <void method="set">
         <object idref="Point24"/>
         <int>809</int>
        </void>
       </void>
       <void class="java.awt.Point" method="getField">
        <string>y</string>
        <void method="set">
         <object idref="Point24"/>
         <int>549</int>
        </void>
       </void>
      </void>
      <void id="Point25" index="1">
       <void class="java.awt.Point" method="getField">
        <string>x</string>
        <void method="set">
         <object idref="Point25"/>
         <int>840</int>
        </void>
       </void>
       <void class="java.awt.Point" method="getField">
        <string>y</string>
        <void method="set">
         <object idref="Point25"/>
         <int>486</int>
        </void>
       </void>
      </void>
     </void>
     <void property="points">
      <object idref="PointArray14"/>
     </void>
     <void property="strokeWidth">
      <float>1.0</float>
     </void>
    </object>
   </void>
   <void method="add">
    <object class="net.sf.jaxodraw.object.text.JaxoLatexText" id="JaxoLatexText4">
     <void property="allign">
      <int>2</int>
     </void>
     <void property="color">
      <object idref="Color0"/>
     </void>
     <void property="latexTextSize">
      <int>9</int>
     </void>
     <void id="PointArray15" property="points">
      <void id="Point26" index="0">
       <void class="java.awt.Point" method="getField">
        <string>x</string>
        <void method="set">
         <object idref="Point26"/>
         <int>711</int>
        </void>
       </void>
       <void class="java.awt.Point" method="getField">
        <string>y</string>
        <void method="set">
         <object idref="Point26"/>
         <int>503</int>
        </void>
       </void>
      </void>
     </void>
     <void property="points">
      <object idref="PointArray15"/>
     </void>
     <void property="textString">
      <string>R_q(z_1+f_1\Pi_0^*)</string>
     </void>
    </object>
   </void>
   <void method="add">
    <object class="net.sf.jaxodraw.object.line.JaxoPLine" id="JaxoPLine1">
     <void property="DLSeparation">
      <float>2.0</float>
     </void>
     <void property="amp">
      <int>15</int>
     </void>
     <void property="color">
      <object idref="Color0"/>
     </void>
     <void id="PointArray16" property="points">
      <void id="Point27" index="0">
       <void class="java.awt.Point" method="getField">
        <string>x</string>
        <void method="set">
         <object idref="Point27"/>
         <int>696</int>
        </void>
       </void>
       <void class="java.awt.Point" method="getField">
        <string>y</string>
        <void method="set">
         <object idref="Point27"/>
         <int>551</int>
        </void>
       </void>
      </void>
      <void id="Point28" index="1">
       <void class="java.awt.Point" method="getField">
        <string>x</string>
        <void method="set">
         <object idref="Point28"/>
         <int>807</int>
        </void>
       </void>
       <void class="java.awt.Point" method="getField">
        <string>y</string>
        <void method="set">
         <object idref="Point28"/>
         <int>550</int>
        </void>
       </void>
      </void>
     </void>
     <void property="points">
      <object idref="PointArray16"/>
     </void>
     <void property="strokeWidth">
      <float>1.0</float>
     </void>
     <void property="wiggles">
      <int>6</int>
     </void>
    </object>
   </void>
   <void method="add">
    <object class="net.sf.jaxodraw.object.vertex.JaxoVertexT2" id="JaxoVertexT21">
     <void property="color">
      <object idref="Color0"/>
     </void>
     <void property="fillColor">
      <object idref="Color1"/>
     </void>
     <void id="PointArray17" property="points">
      <void id="Point29" index="0">
       <void class="java.awt.Point" method="getField">
        <string>x</string>
        <void method="set">
         <object idref="Point29"/>
         <int>750</int>
        </void>
       </void>
       <void class="java.awt.Point" method="getField">
        <string>y</string>
        <void method="set">
         <object idref="Point29"/>
         <int>551</int>
        </void>
       </void>
      </void>
      <void id="Point30" index="1">
       <void class="java.awt.Point" method="getField">
        <string>x</string>
        <void method="set">
         <object idref="Point30"/>
         <int>758</int>
        </void>
       </void>
       <void class="java.awt.Point" method="getField">
        <string>y</string>
        <void method="set">
         <object idref="Point30"/>
         <int>559</int>
        </void>
       </void>
      </void>
     </void>
     <void property="points">
      <object idref="PointArray17"/>
     </void>
     <void property="strokeWidth">
      <float>1.0</float>
     </void>
    </object>
   </void>
   <void method="add">
    <object class="net.sf.jaxodraw.object.line.JaxoFLine" id="JaxoFLine8">
     <void property="DLSeparation">
      <float>2.0</float>
     </void>
     <void property="amp">
      <int>15</int>
     </void>
     <void property="arrowPosition">
      <float>0.5</float>
     </void>
     <void property="color">
      <object idref="Color0"/>
     </void>
     <void property="paintArrow">
      <boolean>true</boolean>
     </void>
     <void id="PointArray18" property="points">
      <void id="Point31" index="0">
       <void class="java.awt.Point" method="getField">
        <string>x</string>
        <void method="set">
         <object idref="Point31"/>
         <int>309</int>
        </void>
       </void>
       <void class="java.awt.Point" method="getField">
        <string>y</string>
        <void method="set">
         <object idref="Point31"/>
         <int>616</int>
        </void>
       </void>
      </void>
      <void id="Point32" index="1">
       <void class="java.awt.Point" method="getField">
        <string>x</string>
        <void method="set">
         <object idref="Point32"/>
         <int>340</int>
        </void>
       </void>
       <void class="java.awt.Point" method="getField">
        <string>y</string>
        <void method="set">
         <object idref="Point32"/>
         <int>547</int>
        </void>
       </void>
      </void>
     </void>
     <void property="points">
      <object idref="PointArray18"/>
     </void>
     <void property="strokeWidth">
      <float>1.0</float>
     </void>
    </object>
   </void>
   <void method="add">
    <object class="net.sf.jaxodraw.object.line.JaxoFLine" id="JaxoFLine9">
     <void property="DLSeparation">
      <float>2.0</float>
     </void>
     <void property="amp">
      <int>15</int>
     </void>
     <void property="arrowPosition">
      <float>0.5</float>
     </void>
     <void property="color">
      <object idref="Color0"/>
     </void>
     <void property="paintArrow">
      <boolean>true</boolean>
     </void>
     <void id="PointArray19" property="points">
      <void id="Point33" index="0">
       <void class="java.awt.Point" method="getField">
        <string>x</string>
        <void method="set">
         <object idref="Point33"/>
         <int>340</int>
        </void>
       </void>
       <void class="java.awt.Point" method="getField">
        <string>y</string>
        <void method="set">
         <object idref="Point33"/>
         <int>545</int>
        </void>
       </void>
      </void>
      <void id="Point34" index="1">
       <void class="java.awt.Point" method="getField">
        <string>x</string>
        <void method="set">
         <object idref="Point34"/>
         <int>307</int>
        </void>
       </void>
       <void class="java.awt.Point" method="getField">
        <string>y</string>
        <void method="set">
         <object idref="Point34"/>
         <int>473</int>
        </void>
       </void>
      </void>
     </void>
     <void property="points">
      <object idref="PointArray19"/>
     </void>
     <void property="strokeWidth">
      <float>1.0</float>
     </void>
    </object>
   </void>
   <void method="add">
    <object class="net.sf.jaxodraw.object.line.JaxoFLine" id="JaxoFLine10">
     <void property="DLSeparation">
      <float>2.0</float>
     </void>
     <void property="amp">
      <int>15</int>
     </void>
     <void property="arrowPosition">
      <float>0.5</float>
     </void>
     <void property="color">
      <object idref="Color0"/>
     </void>
     <void property="paintArrow">
      <boolean>true</boolean>
     </void>
     <void id="PointArray20" property="points">
      <void id="Point35" index="0">
       <void class="java.awt.Point" method="getField">
        <string>x</string>
        <void method="set">
         <object idref="Point35"/>
         <int>546</int>
        </void>
       </void>
       <void class="java.awt.Point" method="getField">
        <string>y</string>
        <void method="set">
         <object idref="Point35"/>
         <int>617</int>
        </void>
       </void>
      </void>
      <void id="Point36" index="1">
       <void class="java.awt.Point" method="getField">
        <string>x</string>
        <void method="set">
         <object idref="Point36"/>
         <int>513</int>
        </void>
       </void>
       <void class="java.awt.Point" method="getField">
        <string>y</string>
        <void method="set">
         <object idref="Point36"/>
         <int>568</int>
        </void>
       </void>
      </void>
     </void>
     <void property="points">
      <object idref="PointArray20"/>
     </void>
     <void property="strokeWidth">
      <float>1.0</float>
     </void>
    </object>
   </void>
   <void method="add">
    <object class="net.sf.jaxodraw.object.line.JaxoFLine" id="JaxoFLine11">
     <void property="DLSeparation">
      <float>2.0</float>
     </void>
     <void property="amp">
      <int>15</int>
     </void>
     <void property="arrowPosition">
      <float>0.5</float>
     </void>
     <void property="color">
      <object idref="Color0"/>
     </void>
     <void property="paintArrow">
      <boolean>true</boolean>
     </void>
     <void id="PointArray21" property="points">
      <void id="Point37" index="0">
       <void class="java.awt.Point" method="getField">
        <string>x</string>
        <void method="set">
         <object idref="Point37"/>
         <int>512</int>
        </void>
       </void>
       <void class="java.awt.Point" method="getField">
        <string>y</string>
        <void method="set">
         <object idref="Point37"/>
         <int>512</int>
        </void>
       </void>
      </void>
      <void id="Point38" index="1">
       <void class="java.awt.Point" method="getField">
        <string>x</string>
        <void method="set">
         <object idref="Point38"/>
         <int>546</int>
        </void>
       </void>
       <void class="java.awt.Point" method="getField">
        <string>y</string>
        <void method="set">
         <object idref="Point38"/>
         <int>474</int>
        </void>
       </void>
      </void>
     </void>
     <void property="points">
      <object idref="PointArray21"/>
     </void>
     <void property="strokeWidth">
      <float>1.0</float>
     </void>
    </object>
   </void>
   <void method="add">
    <object class="net.sf.jaxodraw.object.line.JaxoPLine" id="JaxoPLine2">
     <void property="DLSeparation">
      <float>2.0</float>
     </void>
     <void property="amp">
      <int>15</int>
     </void>
     <void id="JaxoDefaultArrow0" property="arrow">
      <void id="Color2" property="color"/>
     </void>
     <void property="color">
      <object idref="Color2"/>
     </void>
     <void id="PointArray22" property="points">
      <void id="Point39" index="0">
       <void class="java.awt.Point" method="getField">
        <string>x</string>
        <void method="set">
         <object idref="Point39"/>
         <int>341</int>
        </void>
       </void>
       <void class="java.awt.Point" method="getField">
        <string>y</string>
        <void method="set">
         <object idref="Point39"/>
         <int>547</int>
        </void>
       </void>
      </void>
      <void id="Point40" index="1">
       <void class="java.awt.Point" method="getField">
        <string>x</string>
        <void method="set">
         <object idref="Point40"/>
         <int>387</int>
        </void>
       </void>
       <void class="java.awt.Point" method="getField">
        <string>y</string>
        <void method="set">
         <object idref="Point40"/>
         <int>547</int>
        </void>
       </void>
      </void>
     </void>
     <void property="points">
      <object idref="PointArray22"/>
     </void>
     <void property="strokeWidth">
      <float>1.0</float>
     </void>
     <void property="wiggles">
      <int>2</int>
     </void>
    </object>
   </void>
   <void method="add">
    <object class="net.sf.jaxodraw.object.arc.JaxoFArc" id="JaxoFArc0">
     <void property="DLSeparation">
      <float>2.0</float>
     </void>
     <void property="amp">
      <int>15</int>
     </void>
     <void property="arrowPosition">
      <float>0.5</float>
     </void>
     <void property="color">
      <object idref="Color2"/>
     </void>
     <void property="paintArrow">
      <boolean>true</boolean>
     </void>
     <void id="PointArray23" property="points">
      <void id="Point41" index="0">
       <void class="java.awt.Point" method="getField">
        <string>x</string>
        <void method="set">
         <object idref="Point41"/>
         <int>513</int>
        </void>
       </void>
       <void class="java.awt.Point" method="getField">
        <string>y</string>
        <void method="set">
         <object idref="Point41"/>
         <int>514</int>
        </void>
       </void>
      </void>
      <void id="Point42" index="1">
       <void class="java.awt.Point" method="getField">
        <string>x</string>
        <void method="set">
         <object idref="Point42"/>
         <int>466</int>
        </void>
       </void>
       <void class="java.awt.Point" method="getField">
        <string>y</string>
        <void method="set">
         <object idref="Point42"/>
         <int>495</int>
        </void>
       </void>
      </void>
      <void id="Point43" index="2">
       <void class="java.awt.Point" method="getField">
        <string>x</string>
        <void method="set">
         <object idref="Point43"/>
         <int>389</int>
        </void>
       </void>
       <void class="java.awt.Point" method="getField">
        <string>y</string>
        <void method="set">
         <object idref="Point43"/>
         <int>545</int>
        </void>
       </void>
      </void>
     </void>
     <void property="points">
      <object idref="PointArray23"/>
     </void>
     <void property="strokeWidth">
      <float>1.0</float>
     </void>
    </object>
   </void>
   <void method="add">
    <object class="net.sf.jaxodraw.object.arc.JaxoFArc" id="JaxoFArc1">
     <void property="DLSeparation">
      <float>2.0</float>
     </void>
     <void property="amp">
      <int>15</int>
     </void>
     <void property="arrowPosition">
      <float>0.5</float>
     </void>
     <void property="color">
      <object idref="Color2"/>
     </void>
     <void property="paintArrow">
      <boolean>true</boolean>
     </void>
     <void id="PointArray24" property="points">
      <void id="Point44" index="0">
       <void class="java.awt.Point" method="getField">
        <string>x</string>
        <void method="set">
         <object idref="Point44"/>
         <int>391</int>
        </void>
       </void>
       <void class="java.awt.Point" method="getField">
        <string>y</string>
        <void method="set">
         <object idref="Point44"/>
         <int>548</int>
        </void>
       </void>
      </void>
      <void id="Point45" index="1">
       <void class="java.awt.Point" method="getField">
        <string>x</string>
        <void method="set">
         <object idref="Point45"/>
         <int>489</int>
        </void>
       </void>
       <void class="java.awt.Point" method="getField">
        <string>y</string>
        <void method="set">
         <object idref="Point45"/>
         <int>584</int>
        </void>
       </void>
      </void>
      <void id="Point46" index="2">
       <void class="java.awt.Point" method="getField">
        <string>x</string>
        <void method="set">
         <object idref="Point46"/>
         <int>514</int>
        </void>
       </void>
       <void class="java.awt.Point" method="getField">
        <string>y</string>
        <void method="set">
         <object idref="Point46"/>
         <int>569</int>
        </void>
       </void>
      </void>
     </void>
     <void property="points">
      <object idref="PointArray24"/>
     </void>
     <void property="strokeWidth">
      <float>1.0</float>
     </void>
    </object>
   </void>
   <void method="add">
    <object class="net.sf.jaxodraw.object.line.JaxoPLine" id="JaxoPLine3">
     <void property="DLSeparation">
      <float>2.0</float>
     </void>
     <void property="amp">
      <int>10</int>
     </void>
     <void property="color">
      <object idref="Color2"/>
     </void>
     <void id="PointArray25" property="points">
      <void id="Point47" index="0">
       <void class="java.awt.Point" method="getField">
        <string>x</string>
        <void method="set">
         <object idref="Point47"/>
         <int>512</int>
        </void>
       </void>
       <void class="java.awt.Point" method="getField">
        <string>y</string>
        <void method="set">
         <object idref="Point47"/>
         <int>513</int>
        </void>
       </void>
      </void>
      <void id="Point48" index="1">
       <void class="java.awt.Point" method="getField">
        <string>x</string>
        <void method="set">
         <object idref="Point48"/>
         <int>516</int>
        </void>
       </void>
       <void class="java.awt.Point" method="getField">
        <string>y</string>
        <void method="set">
         <object idref="Point48"/>
         <int>569</int>
        </void>
       </void>
      </void>
     </void>
     <void property="points">
      <object idref="PointArray25"/>
     </void>
     <void property="strokeWidth">
      <float>1.0</float>
     </void>
     <void property="wiggles">
      <int>3</int>
     </void>
    </object>
   </void>
   <void method="add">
    <object class="net.sf.jaxodraw.object.text.JaxoLatexText" id="JaxoLatexText5">
     <void property="allign">
      <int>2</int>
     </void>
     <void property="color">
      <object idref="Color0"/>
     </void>
     <void property="latexTextSize">
      <int>9</int>
     </void>
     <void id="PointArray26" property="points">
      <void id="Point49" index="0">
       <void class="java.awt.Point" method="getField">
        <string>x</string>
        <void method="set">
         <object idref="Point49"/>
         <int>425</int>
        </void>
       </void>
       <void class="java.awt.Point" method="getField">
        <string>y</string>
        <void method="set">
         <object idref="Point49"/>
         <int>468</int>
        </void>
       </void>
      </void>
     </void>
     <void property="points">
      <object idref="PointArray26"/>
     </void>
     <void property="textString">
      <string>\gamma_1^2</string>
     </void>
    </object>
   </void>
   <void method="add">
    <object class="net.sf.jaxodraw.object.text.JaxoLatexText" id="JaxoLatexText6">
     <void property="allign">
      <int>2</int>
     </void>
     <void property="color">
      <object idref="Color0"/>
     </void>
     <void property="latexTextSize">
      <int>9</int>
     </void>
     <void id="PointArray27" property="points">
      <void id="Point50" index="0">
       <void class="java.awt.Point" method="getField">
        <string>x</string>
        <void method="set">
         <object idref="Point50"/>
         <int>586</int>
        </void>
       </void>
       <void class="java.awt.Point" method="getField">
        <string>y</string>
        <void method="set">
         <object idref="Point50"/>
         <int>561</int>
        </void>
       </void>
      </void>
     </void>
     <void property="points">
      <object idref="PointArray27"/>
     </void>
     <void property="textString">
      <string>+</string>
     </void>
    </object>
   </void>
   <void method="add">
    <object class="net.sf.jaxodraw.object.text.JaxoLatexText" id="JaxoLatexText7">
     <void property="allign">
      <int>2</int>
     </void>
     <void property="color">
      <object idref="Color0"/>
     </void>
     <void property="latexTextSize">
      <int>9</int>
     </void>
     <void id="PointArray28" property="points">
      <void id="Point51" index="0">
       <void class="java.awt.Point" method="getField">
        <string>x</string>
        <void method="set">
         <object idref="Point51"/>
         <int>576</int>
        </void>
       </void>
       <void class="java.awt.Point" method="getField">
        <string>y</string>
        <void method="set">
         <object idref="Point51"/>
         <int>762</int>
        </void>
       </void>
      </void>
     </void>
     <void property="points">
      <object idref="PointArray28"/>
     </void>
     <void property="textString">
      <string>+</string>
     </void>
    </object>
   </void>
   <void method="add">
    <object class="net.sf.jaxodraw.object.line.JaxoFLine" id="JaxoFLine12">
     <void property="DLSeparation">
      <float>2.0</float>
     </void>
     <void property="amp">
      <int>15</int>
     </void>
     <void property="arrowPosition">
      <float>0.5</float>
     </void>
     <void property="color">
      <object idref="Color0"/>
     </void>
     <void property="paintArrow">
      <boolean>true</boolean>
     </void>
     <void id="PointArray29" property="points">
      <void id="Point52" index="0">
       <void class="java.awt.Point" method="getField">
        <string>x</string>
        <void method="set">
         <object idref="Point52"/>
         <int>305</int>
        </void>
       </void>
       <void class="java.awt.Point" method="getField">
        <string>y</string>
        <void method="set">
         <object idref="Point52"/>
         <int>821</int>
        </void>
       </void>
      </void>
      <void id="Point53" index="1">
       <void class="java.awt.Point" method="getField">
        <string>x</string>
        <void method="set">
         <object idref="Point53"/>
         <int>340</int>
        </void>
       </void>
       <void class="java.awt.Point" method="getField">
        <string>y</string>
        <void method="set">
         <object idref="Point53"/>
         <int>771</int>
        </void>
       </void>
      </void>
     </void>
     <void property="points">
      <object idref="PointArray29"/>
     </void>
     <void property="strokeWidth">
      <float>1.0</float>
     </void>
    </object>
   </void>
   <void method="add">
    <object class="net.sf.jaxodraw.object.line.JaxoFLine" id="JaxoFLine13">
     <void property="DLSeparation">
      <float>2.0</float>
     </void>
     <void property="amp">
      <int>15</int>
     </void>
     <void property="arrowPosition">
      <float>0.5</float>
     </void>
     <void property="color">
      <object idref="Color0"/>
     </void>
     <void property="paintArrow">
      <boolean>true</boolean>
     </void>
     <void id="PointArray30" property="points">
      <void id="Point54" index="0">
       <void class="java.awt.Point" method="getField">
        <string>x</string>
        <void method="set">
         <object idref="Point54"/>
         <int>337</int>
        </void>
       </void>
       <void class="java.awt.Point" method="getField">
        <string>y</string>
        <void method="set">
         <object idref="Point54"/>
         <int>720</int>
        </void>
       </void>
      </void>
      <void id="Point55" index="1">
       <void class="java.awt.Point" method="getField">
        <string>x</string>
        <void method="set">
         <object idref="Point55"/>
         <int>304</int>
        </void>
       </void>
       <void class="java.awt.Point" method="getField">
        <string>y</string>
        <void method="set">
         <object idref="Point55"/>
         <int>676</int>
        </void>
       </void>
      </void>
     </void>
     <void property="points">
      <object idref="PointArray30"/>
     </void>
     <void property="strokeWidth">
      <float>1.0</float>
     </void>
    </object>
   </void>
   <void method="add">
    <object class="net.sf.jaxodraw.object.line.JaxoFLine" id="JaxoFLine14">
     <void property="DLSeparation">
      <float>2.0</float>
     </void>
     <void property="amp">
      <int>15</int>
     </void>
     <void property="arrowPosition">
      <float>0.5</float>
     </void>
     <void property="color">
      <object idref="Color0"/>
     </void>
     <void property="paintArrow">
      <boolean>true</boolean>
     </void>
     <void id="PointArray31" property="points">
      <void id="Point56" index="0">
       <void class="java.awt.Point" method="getField">
        <string>x</string>
        <void method="set">
         <object idref="Point56"/>
         <int>544</int>
        </void>
       </void>
       <void class="java.awt.Point" method="getField">
        <string>y</string>
        <void method="set">
         <object idref="Point56"/>
         <int>815</int>
        </void>
       </void>
      </void>
      <void id="Point57" index="1">
       <void class="java.awt.Point" method="getField">
        <string>x</string>
        <void method="set">
         <object idref="Point57"/>
         <int>530</int>
        </void>
       </void>
       <void class="java.awt.Point" method="getField">
        <string>y</string>
        <void method="set">
         <object idref="Point57"/>
         <int>776</int>
        </void>
       </void>
      </void>
     </void>
     <void property="points">
      <object idref="PointArray31"/>
     </void>
     <void property="strokeWidth">
      <float>1.0</float>
     </void>
    </object>
   </void>
   <void method="add">
    <object class="net.sf.jaxodraw.object.line.JaxoFLine" id="JaxoFLine15">
     <void property="DLSeparation">
      <float>2.0</float>
     </void>
     <void property="amp">
      <int>15</int>
     </void>
     <void property="arrowPosition">
      <float>0.5</float>
     </void>
     <void property="color">
      <object idref="Color0"/>
     </void>
     <void property="paintArrow">
      <boolean>true</boolean>
     </void>
     <void id="PointArray32" property="points">
      <void id="Point58" index="0">
       <void class="java.awt.Point" method="getField">
        <string>x</string>
        <void method="set">
         <object idref="Point58"/>
         <int>528</int>
        </void>
       </void>
       <void class="java.awt.Point" method="getField">
        <string>y</string>
        <void method="set">
         <object idref="Point58"/>
         <int>721</int>
        </void>
       </void>
      </void>
      <void id="Point59" index="1">
       <void class="java.awt.Point" method="getField">
        <string>x</string>
        <void method="set">
         <object idref="Point59"/>
         <int>548</int>
        </void>
       </void>
       <void class="java.awt.Point" method="getField">
        <string>y</string>
        <void method="set">
         <object idref="Point59"/>
         <int>686</int>
        </void>
       </void>
      </void>
     </void>
     <void property="points">
      <object idref="PointArray32"/>
     </void>
     <void property="strokeWidth">
      <float>1.0</float>
     </void>
    </object>
   </void>
   <void method="add">
    <object class="net.sf.jaxodraw.object.arc.JaxoFArc" id="JaxoFArc2">
     <void property="DLSeparation">
      <float>2.0</float>
     </void>
     <void property="amp">
      <int>15</int>
     </void>
     <void property="arrowPosition">
      <float>0.5</float>
     </void>
     <void property="color">
      <object idref="Color2"/>
     </void>
     <void property="paintArrow">
      <boolean>true</boolean>
     </void>
     <void id="PointArray33" property="points">
      <void id="Point60" index="0">
       <void class="java.awt.Point" method="getField">
        <string>x</string>
        <void method="set">
         <object idref="Point60"/>
         <int>530</int>
        </void>
       </void>
       <void class="java.awt.Point" method="getField">
        <string>y</string>
        <void method="set">
         <object idref="Point60"/>
         <int>775</int>
        </void>
       </void>
      </void>
      <void id="Point61" index="1">
       <void class="java.awt.Point" method="getField">
        <string>x</string>
        <void method="set">
         <object idref="Point61"/>
         <int>467</int>
        </void>
       </void>
       <void class="java.awt.Point" method="getField">
        <string>y</string>
        <void method="set">
         <object idref="Point61"/>
         <int>703</int>
        </void>
       </void>
      </void>
      <void id="Point62" index="2">
       <void class="java.awt.Point" method="getField">
        <string>x</string>
        <void method="set">
         <object idref="Point62"/>
         <int>337</int>
        </void>
       </void>
       <void class="java.awt.Point" method="getField">
        <string>y</string>
        <void method="set">
         <object idref="Point62"/>
         <int>718</int>
        </void>
       </void>
      </void>
     </void>
     <void property="points">
      <object idref="PointArray33"/>
     </void>
     <void property="strokeWidth">
      <float>1.0</float>
     </void>
    </object>
   </void>
   <void method="add">
    <object class="net.sf.jaxodraw.object.arc.JaxoFArc" id="JaxoFArc3">
     <void property="DLSeparation">
      <float>2.0</float>
     </void>
     <void property="amp">
      <int>15</int>
     </void>
     <void property="arrowPosition">
      <float>0.5</float>
     </void>
     <void property="color">
      <object idref="Color2"/>
     </void>
     <void property="paintArrow">
      <boolean>true</boolean>
     </void>
     <void id="PointArray34" property="points">
      <void id="Point63" index="0">
       <void class="java.awt.Point" method="getField">
        <string>x</string>
        <void method="set">
         <object idref="Point63"/>
         <int>342</int>
        </void>
       </void>
       <void class="java.awt.Point" method="getField">
        <string>y</string>
        <void method="set">
         <object idref="Point63"/>
         <int>773</int>
        </void>
       </void>
      </void>
      <void id="Point64" index="1">
       <void class="java.awt.Point" method="getField">
        <string>x</string>
        <void method="set">
         <object idref="Point64"/>
         <int>461</int>
        </void>
       </void>
       <void class="java.awt.Point" method="getField">
        <string>y</string>
        <void method="set">
         <object idref="Point64"/>
         <int>783</int>
        </void>
       </void>
      </void>
      <void id="Point65" index="2">
       <void class="java.awt.Point" method="getField">
        <string>x</string>
        <void method="set">
         <object idref="Point65"/>
         <int>528</int>
        </void>
       </void>
       <void class="java.awt.Point" method="getField">
        <string>y</string>
        <void method="set">
         <object idref="Point65"/>
         <int>721</int>
        </void>
       </void>
      </void>
     </void>
     <void property="points">
      <object idref="PointArray34"/>
     </void>
     <void property="strokeWidth">
      <float>1.0</float>
     </void>
    </object>
   </void>
   <void method="add">
    <object class="net.sf.jaxodraw.object.line.JaxoPLine" id="JaxoPLine4">
     <void property="DLSeparation">
      <float>2.0</float>
     </void>
     <void property="amp">
      <int>10</int>
     </void>
     <void property="color">
      <object idref="Color2"/>
     </void>
     <void id="PointArray35" property="points">
      <void id="Point66" index="0">
       <void class="java.awt.Point" method="getField">
        <string>x</string>
        <void method="set">
         <object idref="Point66"/>
         <int>339</int>
        </void>
       </void>
       <void class="java.awt.Point" method="getField">
        <string>y</string>
        <void method="set">
         <object idref="Point66"/>
         <int>721</int>
        </void>
       </void>
      </void>
      <void id="Point67" index="1">
       <void class="java.awt.Point" method="getField">
        <string>x</string>
        <void method="set">
         <object idref="Point67"/>
         <int>339</int>
        </void>
       </void>
       <void class="java.awt.Point" method="getField">
        <string>y</string>
        <void method="set">
         <object idref="Point67"/>
         <int>772</int>
        </void>
       </void>
      </void>
     </void>
     <void property="points">
      <object idref="PointArray35"/>
     </void>
     <void property="strokeWidth">
      <float>1.0</float>
     </void>
     <void property="wiggles">
      <int>3</int>
     </void>
    </object>
   </void>
   <void method="add">
    <object class="net.sf.jaxodraw.object.line.JaxoPLine" id="JaxoPLine5">
     <void property="DLSeparation">
      <float>2.0</float>
     </void>
     <void property="amp">
      <int>9</int>
     </void>
     <void property="color">
      <object idref="Color2"/>
     </void>
     <void id="PointArray36" property="points">
      <void id="Point68" index="0">
       <void class="java.awt.Point" method="getField">
        <string>x</string>
        <void method="set">
         <object idref="Point68"/>
         <int>484</int>
        </void>
       </void>
       <void class="java.awt.Point" method="getField">
        <string>y</string>
        <void method="set">
         <object idref="Point68"/>
         <int>717</int>
        </void>
       </void>
      </void>
      <void id="Point69" index="1">
       <void class="java.awt.Point" method="getField">
        <string>x</string>
        <void method="set">
         <object idref="Point69"/>
         <int>487</int>
        </void>
       </void>
       <void class="java.awt.Point" method="getField">
        <string>y</string>
        <void method="set">
         <object idref="Point69"/>
         <int>770</int>
        </void>
       </void>
      </void>
     </void>
     <void property="points">
      <object idref="PointArray36"/>
     </void>
     <void property="strokeWidth">
      <float>1.0</float>
     </void>
     <void property="wiggles">
      <int>3</int>
     </void>
    </object>
   </void>
   <void method="add">
    <object class="net.sf.jaxodraw.object.line.JaxoFLine" id="JaxoFLine16">
     <void property="DLSeparation">
      <float>2.0</float>
     </void>
     <void property="amp">
      <int>15</int>
     </void>
     <void property="arrowPosition">
      <float>0.5</float>
     </void>
     <void property="color">
      <object idref="Color0"/>
     </void>
     <void property="paintArrow">
      <boolean>true</boolean>
     </void>
     <void id="PointArray37" property="points">
      <void id="Point70" index="0">
       <void class="java.awt.Point" method="getField">
        <string>x</string>
        <void method="set">
         <object idref="Point70"/>
         <int>318</int>
        </void>
       </void>
       <void class="java.awt.Point" method="getField">
        <string>y</string>
        <void method="set">
         <object idref="Point70"/>
         <int>394</int>
        </void>
       </void>
      </void>
      <void id="Point71" index="1">
       <void class="java.awt.Point" method="getField">
        <string>x</string>
        <void method="set">
         <object idref="Point71"/>
         <int>343</int>
        </void>
       </void>
       <void class="java.awt.Point" method="getField">
        <string>y</string>
        <void method="set">
         <object idref="Point71"/>
         <int>351</int>
        </void>
       </void>
      </void>
     </void>
     <void property="points">
      <object idref="PointArray37"/>
     </void>
     <void property="strokeWidth">
      <float>1.0</float>
     </void>
    </object>
   </void>
   <void method="add">
    <object class="net.sf.jaxodraw.object.line.JaxoFLine" id="JaxoFLine17">
     <void property="DLSeparation">
      <float>2.0</float>
     </void>
     <void property="amp">
      <int>15</int>
     </void>
     <void property="arrowPosition">
      <float>0.5</float>
     </void>
     <void property="color">
      <object idref="Color0"/>
     </void>
     <void property="paintArrow">
      <boolean>true</boolean>
     </void>
     <void id="PointArray38" property="points">
      <void id="Point72" index="0">
       <void class="java.awt.Point" method="getField">
        <string>x</string>
        <void method="set">
         <object idref="Point72"/>
         <int>343</int>
        </void>
       </void>
       <void class="java.awt.Point" method="getField">
        <string>y</string>
        <void method="set">
         <object idref="Point72"/>
         <int>296</int>
        </void>
       </void>
      </void>
      <void id="Point73" index="1">
       <void class="java.awt.Point" method="getField">
        <string>x</string>
        <void method="set">
         <object idref="Point73"/>
         <int>316</int>
        </void>
       </void>
       <void class="java.awt.Point" method="getField">
        <string>y</string>
        <void method="set">
         <object idref="Point73"/>
         <int>258</int>
        </void>
       </void>
      </void>
     </void>
     <void property="points">
      <object idref="PointArray38"/>
     </void>
     <void property="strokeWidth">
      <float>1.0</float>
     </void>
    </object>
   </void>
   <void method="add">
    <object class="net.sf.jaxodraw.object.line.JaxoFLine" id="JaxoFLine18">
     <void property="DLSeparation">
      <float>2.0</float>
     </void>
     <void property="amp">
      <int>15</int>
     </void>
     <void property="arrowPosition">
      <float>0.5</float>
     </void>
     <void property="color">
      <object idref="Color0"/>
     </void>
     <void property="paintArrow">
      <boolean>true</boolean>
     </void>
     <void id="PointArray39" property="points">
      <void id="Point74" index="0">
       <void class="java.awt.Point" method="getField">
        <string>x</string>
        <void method="set">
         <object idref="Point74"/>
         <int>547</int>
        </void>
       </void>
       <void class="java.awt.Point" method="getField">
        <string>y</string>
        <void method="set">
         <object idref="Point74"/>
         <int>388</int>
        </void>
       </void>
      </void>
      <void id="Point75" index="1">
       <void class="java.awt.Point" method="getField">
        <string>x</string>
        <void method="set">
         <object idref="Point75"/>
         <int>513</int>
        </void>
       </void>
       <void class="java.awt.Point" method="getField">
        <string>y</string>
        <void method="set">
         <object idref="Point75"/>
         <int>321</int>
        </void>
       </void>
      </void>
     </void>
     <void property="points">
      <object idref="PointArray39"/>
     </void>
     <void property="strokeWidth">
      <float>1.0</float>
     </void>
    </object>
   </void>
   <void method="add">
    <object class="net.sf.jaxodraw.object.line.JaxoFLine" id="JaxoFLine19">
     <void property="DLSeparation">
      <float>2.0</float>
     </void>
     <void property="amp">
      <int>15</int>
     </void>
     <void property="arrowPosition">
      <float>0.5</float>
     </void>
     <void property="color">
      <object idref="Color0"/>
     </void>
     <void property="paintArrow">
      <boolean>true</boolean>
     </void>
     <void id="PointArray40" property="points">
      <void id="Point76" index="0">
       <void class="java.awt.Point" method="getField">
        <string>x</string>
        <void method="set">
         <object idref="Point76"/>
         <int>513</int>
        </void>
       </void>
       <void class="java.awt.Point" method="getField">
        <string>y</string>
        <void method="set">
         <object idref="Point76"/>
         <int>321</int>
        </void>
       </void>
      </void>
      <void id="Point77" index="1">
       <void class="java.awt.Point" method="getField">
        <string>x</string>
        <void method="set">
         <object idref="Point77"/>
         <int>547</int>
        </void>
       </void>
       <void class="java.awt.Point" method="getField">
        <string>y</string>
        <void method="set">
         <object idref="Point77"/>
         <int>258</int>
        </void>
       </void>
      </void>
     </void>
     <void property="points">
      <object idref="PointArray40"/>
     </void>
     <void property="strokeWidth">
      <float>1.0</float>
     </void>
    </object>
   </void>
   <void method="add">
    <object class="net.sf.jaxodraw.object.arc.JaxoFArc" id="JaxoFArc4">
     <void property="DLSeparation">
      <float>2.0</float>
     </void>
     <void property="amp">
      <int>15</int>
     </void>
     <void property="arrowPosition">
      <float>0.5</float>
     </void>
     <void property="color">
      <object idref="Color2"/>
     </void>
     <void property="paintArrow">
      <boolean>true</boolean>
     </void>
     <void id="PointArray41" property="points">
      <void id="Point78" index="0">
       <void class="java.awt.Point" method="getField">
        <string>x</string>
        <void method="set">
         <object idref="Point78"/>
         <int>344</int>
        </void>
       </void>
       <void class="java.awt.Point" method="getField">
        <string>y</string>
        <void method="set">
         <object idref="Point78"/>
         <int>352</int>
        </void>
       </void>
      </void>
      <void id="Point79" index="1">
       <void class="java.awt.Point" method="getField">
        <string>x</string>
        <void method="set">
         <object idref="Point79"/>
         <int>402</int>
        </void>
       </void>
       <void class="java.awt.Point" method="getField">
        <string>y</string>
        <void method="set">
         <object idref="Point79"/>
         <int>369</int>
        </void>
       </void>
      </void>
      <void id="Point80" index="2">
       <void class="java.awt.Point" method="getField">
        <string>x</string>
        <void method="set">
         <object idref="Point80"/>
         <int>467</int>
        </void>
       </void>
       <void class="java.awt.Point" method="getField">
        <string>y</string>
        <void method="set">
         <object idref="Point80"/>
         <int>320</int>
        </void>
       </void>
      </void>
     </void>
     <void property="points">
      <object idref="PointArray41"/>
     </void>
     <void property="strokeWidth">
      <float>1.0</float>
     </void>
    </object>
   </void>
   <void method="add">
    <object class="net.sf.jaxodraw.object.arc.JaxoFArc" id="JaxoFArc5">
     <void property="DLSeparation">
      <float>2.0</float>
     </void>
     <void property="amp">
      <int>15</int>
     </void>
     <void property="arrowPosition">
      <float>0.5</float>
     </void>
     <void property="color">
      <object idref="Color2"/>
     </void>
     <void property="paintArrow">
      <boolean>true</boolean>
     </void>
     <void id="PointArray42" property="points">
      <void id="Point81" index="0">
       <void class="java.awt.Point" method="getField">
        <string>x</string>
        <void method="set">
         <object idref="Point81"/>
         <int>467</int>
        </void>
       </void>
       <void class="java.awt.Point" method="getField">
        <string>y</string>
        <void method="set">
         <object idref="Point81"/>
         <int>319</int>
        </void>
       </void>
      </void>
      <void id="Point82" index="1">
       <void class="java.awt.Point" method="getField">
        <string>x</string>
        <void method="set">
         <object idref="Point82"/>
         <int>387</int>
        </void>
       </void>
       <void class="java.awt.Point" method="getField">
        <string>y</string>
        <void method="set">
         <object idref="Point82"/>
         <int>276</int>
        </void>
       </void>
      </void>
      <void id="Point83" index="2">
       <void class="java.awt.Point" method="getField">
        <string>x</string>
        <void method="set">
         <object idref="Point83"/>
         <int>342</int>
        </void>
       </void>
       <void class="java.awt.Point" method="getField">
        <string>y</string>
        <void method="set">
         <object idref="Point83"/>
         <int>297</int>
        </void>
       </void>
      </void>
     </void>
     <void property="points">
      <object idref="PointArray42"/>
     </void>
     <void property="strokeWidth">
      <float>1.0</float>
     </void>
    </object>
   </void>
   <void method="add">
    <object class="net.sf.jaxodraw.object.line.JaxoPLine" id="JaxoPLine6">
     <void property="DLSeparation">
      <float>2.0</float>
     </void>
     <void property="amp">
      <int>15</int>
     </void>
     <void property="color">
      <object idref="Color2"/>
     </void>
     <void id="PointArray43" property="points">
      <void id="Point84" index="0">
       <void class="java.awt.Point" method="getField">
        <string>x</string>
        <void method="set">
         <object idref="Point84"/>
         <int>467</int>
        </void>
       </void>
       <void class="java.awt.Point" method="getField">
        <string>y</string>
        <void method="set">
         <object idref="Point84"/>
         <int>320</int>
        </void>
       </void>
      </void>
      <void id="Point85" index="1">
       <void class="java.awt.Point" method="getField">
        <string>x</string>
        <void method="set">
         <object idref="Point85"/>
         <int>513</int>
        </void>
       </void>
       <void class="java.awt.Point" method="getField">
        <string>y</string>
        <void method="set">
         <object idref="Point85"/>
         <int>320</int>
        </void>
       </void>
      </void>
     </void>
     <void property="points">
      <object idref="PointArray43"/>
     </void>
     <void property="strokeWidth">
      <float>1.0</float>
     </void>
     <void property="wiggles">
      <int>2</int>
     </void>
    </object>
   </void>
   <void method="add">
    <object class="net.sf.jaxodraw.object.line.JaxoPLine" id="JaxoPLine7">
     <void property="DLSeparation">
      <float>2.0</float>
     </void>
     <void property="amp">
      <int>10</int>
     </void>
     <void property="color">
      <object idref="Color2"/>
     </void>
     <void id="PointArray44" property="points">
      <void id="Point86" index="0">
       <void class="java.awt.Point" method="getField">
        <string>x</string>
        <void method="set">
         <object idref="Point86"/>
         <int>343</int>
        </void>
       </void>
       <void class="java.awt.Point" method="getField">
        <string>y</string>
        <void method="set">
         <object idref="Point86"/>
         <int>295</int>
        </void>
       </void>
      </void>
      <void id="Point87" index="1">
       <void class="java.awt.Point" method="getField">
        <string>x</string>
        <void method="set">
         <object idref="Point87"/>
         <int>345</int>
        </void>
       </void>
       <void class="java.awt.Point" method="getField">
        <string>y</string>
        <void method="set">
         <object idref="Point87"/>
         <int>350</int>
        </void>
       </void>
      </void>
     </void>
     <void property="points">
      <object idref="PointArray44"/>
     </void>
     <void property="strokeWidth">
      <float>1.0</float>
     </void>
     <void property="wiggles">
      <int>3</int>
     </void>
    </object>
   </void>
   <void method="add">
    <object class="net.sf.jaxodraw.object.text.JaxoLatexText" id="JaxoLatexText8">
     <void property="allign">
      <int>2</int>
     </void>
     <void property="color">
      <object idref="Color0"/>
     </void>
     <void property="latexTextSize">
      <int>9</int>
     </void>
     <void id="PointArray45" property="points">
      <void id="Point88" index="0">
       <void class="java.awt.Point" method="getField">
        <string>x</string>
        <void method="set">
         <object idref="Point88"/>
         <int>420</int>
        </void>
       </void>
       <void class="java.awt.Point" method="getField">
        <string>y</string>
        <void method="set">
         <object idref="Point88"/>
         <int>673</int>
        </void>
       </void>
      </void>
     </void>
     <void property="points">
      <object idref="PointArray45"/>
     </void>
     <void property="textString">
      <string>\gamma_1^3</string>
     </void>
    </object>
   </void>
   <void method="add">
    <object class="net.sf.jaxodraw.object.line.JaxoFLine" id="JaxoFLine20">
     <void property="DLSeparation">
      <float>2.0</float>
     </void>
     <void property="amp">
      <int>15</int>
     </void>
     <void property="arrowPosition">
      <float>0.5</float>
     </void>
     <void property="color">
      <object idref="Color0"/>
     </void>
     <void property="paintArrow">
      <boolean>true</boolean>
     </void>
     <void id="PointArray46" property="points">
      <void id="Point89" index="0">
       <void class="java.awt.Point" method="getField">
        <string>x</string>
        <void method="set">
         <object idref="Point89"/>
         <int>663</int>
        </void>
       </void>
       <void class="java.awt.Point" method="getField">
        <string>y</string>
        <void method="set">
         <object idref="Point89"/>
         <int>817</int>
        </void>
       </void>
      </void>
      <void id="Point90" index="1">
       <void class="java.awt.Point" method="getField">
        <string>x</string>
        <void method="set">
         <object idref="Point90"/>
         <int>694</int>
        </void>
       </void>
       <void class="java.awt.Point" method="getField">
        <string>y</string>
        <void method="set">
         <object idref="Point90"/>
         <int>751</int>
        </void>
       </void>
      </void>
     </void>
     <void property="points">
      <object idref="PointArray46"/>
     </void>
     <void property="strokeWidth">
      <float>1.0</float>
     </void>
    </object>
   </void>
   <void method="add">
    <object class="net.sf.jaxodraw.object.line.JaxoFLine" id="JaxoFLine21">
     <void property="DLSeparation">
      <float>2.0</float>
     </void>
     <void property="amp">
      <int>15</int>
     </void>
     <void property="arrowPosition">
      <float>0.5</float>
     </void>
     <void property="color">
      <object idref="Color0"/>
     </void>
     <void property="paintArrow">
      <boolean>true</boolean>
     </void>
     <void id="PointArray47" property="points">
      <void id="Point91" index="0">
       <void class="java.awt.Point" method="getField">
        <string>x</string>
        <void method="set">
         <object idref="Point91"/>
         <int>694</int>
        </void>
       </void>
       <void class="java.awt.Point" method="getField">
        <string>y</string>
        <void method="set">
         <object idref="Point91"/>
         <int>751</int>
        </void>
       </void>
      </void>
      <void id="Point92" index="1">
       <void class="java.awt.Point" method="getField">
        <string>x</string>
        <void method="set">
         <object idref="Point92"/>
         <int>663</int>
        </void>
       </void>
       <void class="java.awt.Point" method="getField">
        <string>y</string>
        <void method="set">
         <object idref="Point92"/>
         <int>688</int>
        </void>
       </void>
      </void>
     </void>
     <void property="points">
      <object idref="PointArray47"/>
     </void>
     <void property="strokeWidth">
      <float>1.0</float>
     </void>
    </object>
   </void>
   <void method="add">
    <object class="net.sf.jaxodraw.object.line.JaxoFLine" id="JaxoFLine22">
     <void property="DLSeparation">
      <float>2.0</float>
     </void>
     <void property="amp">
      <int>15</int>
     </void>
     <void property="arrowPosition">
      <float>0.5</float>
     </void>
     <void property="color">
      <object idref="Color0"/>
     </void>
     <void property="paintArrow">
      <boolean>true</boolean>
     </void>
     <void id="PointArray48" property="points">
      <void id="Point93" index="0">
       <void class="java.awt.Point" method="getField">
        <string>x</string>
        <void method="set">
         <object idref="Point93"/>
         <int>837</int>
        </void>
       </void>
       <void class="java.awt.Point" method="getField">
        <string>y</string>
        <void method="set">
         <object idref="Point93"/>
         <int>815</int>
        </void>
       </void>
      </void>
      <void id="Point94" index="1">
       <void class="java.awt.Point" method="getField">
        <string>x</string>
        <void method="set">
         <object idref="Point94"/>
         <int>807</int>
        </void>
       </void>
       <void class="java.awt.Point" method="getField">
        <string>y</string>
        <void method="set">
         <object idref="Point94"/>
         <int>749</int>
        </void>
       </void>
      </void>
     </void>
     <void property="points">
      <object idref="PointArray48"/>
     </void>
     <void property="strokeWidth">
      <float>1.0</float>
     </void>
    </object>
   </void>
   <void method="add">
    <object class="net.sf.jaxodraw.object.line.JaxoFLine" id="JaxoFLine23">
     <void property="DLSeparation">
      <float>2.0</float>
     </void>
     <void property="amp">
      <int>15</int>
     </void>
     <void property="arrowPosition">
      <float>0.5</float>
     </void>
     <void property="color">
      <object idref="Color0"/>
     </void>
     <void property="paintArrow">
      <boolean>true</boolean>
     </void>
     <void id="PointArray49" property="points">
      <void id="Point95" index="0">
       <void class="java.awt.Point" method="getField">
        <string>x</string>
        <void method="set">
         <object idref="Point95"/>
         <int>808</int>
        </void>
       </void>
       <void class="java.awt.Point" method="getField">
        <string>y</string>
        <void method="set">
         <object idref="Point95"/>
         <int>749</int>
        </void>
       </void>
      </void>
      <void id="Point96" index="1">
       <void class="java.awt.Point" method="getField">
        <string>x</string>
        <void method="set">
         <object idref="Point96"/>
         <int>839</int>
        </void>
       </void>
       <void class="java.awt.Point" method="getField">
        <string>y</string>
        <void method="set">
         <object idref="Point96"/>
         <int>686</int>
        </void>
       </void>
      </void>
     </void>
     <void property="points">
      <object idref="PointArray49"/>
     </void>
     <void property="strokeWidth">
      <float>1.0</float>
     </void>
    </object>
   </void>
   <void method="add">
    <object class="net.sf.jaxodraw.object.text.JaxoLatexText" id="JaxoLatexText9">
     <void property="allign">
      <int>2</int>
     </void>
     <void property="color">
      <object idref="Color0"/>
     </void>
     <void property="latexTextSize">
      <int>9</int>
     </void>
     <void id="PointArray50" property="points">
      <void id="Point97" index="0">
       <void class="java.awt.Point" method="getField">
        <string>x</string>
        <void method="set">
         <object idref="Point97"/>
         <int>710</int>
        </void>
       </void>
       <void class="java.awt.Point" method="getField">
        <string>y</string>
        <void method="set">
         <object idref="Point97"/>
         <int>703</int>
        </void>
       </void>
      </void>
     </void>
     <void property="points">
      <object idref="PointArray50"/>
     </void>
     <void property="textString">
      <string>f_1\Pi_0^*f_1</string>
     </void>
    </object>
   </void>
   <void method="add">
    <object class="net.sf.jaxodraw.object.line.JaxoPLine" id="JaxoPLine8">
     <void property="DLSeparation">
      <float>2.0</float>
     </void>
     <void property="amp">
      <int>15</int>
     </void>
     <void property="color">
      <object idref="Color0"/>
     </void>
     <void id="PointArray51" property="points">
      <void id="Point98" index="0">
       <void class="java.awt.Point" method="getField">
        <string>x</string>
        <void method="set">
         <object idref="Point98"/>
         <int>695</int>
        </void>
       </void>
       <void class="java.awt.Point" method="getField">
        <string>y</string>
        <void method="set">
         <object idref="Point98"/>
         <int>751</int>
        </void>
       </void>
      </void>
      <void id="Point99" index="1">
       <void class="java.awt.Point" method="getField">
        <string>x</string>
        <void method="set">
         <object idref="Point99"/>
         <int>806</int>
        </void>
       </void>
       <void class="java.awt.Point" method="getField">
        <string>y</string>
        <void method="set">
         <object idref="Point99"/>
         <int>750</int>
        </void>
       </void>
      </void>
     </void>
     <void property="points">
      <object idref="PointArray51"/>
     </void>
     <void property="strokeWidth">
      <float>1.0</float>
     </void>
     <void property="wiggles">
      <int>6</int>
     </void>
    </object>
   </void>
   <void method="add">
    <object class="net.sf.jaxodraw.object.vertex.JaxoVertexT2" id="JaxoVertexT22">
     <void property="color">
      <object idref="Color0"/>
     </void>
     <void property="fillColor">
      <object idref="Color1"/>
     </void>
     <void id="PointArray52" property="points">
      <void id="Point100" index="0">
       <void class="java.awt.Point" method="getField">
        <string>x</string>
        <void method="set">
         <object idref="Point100"/>
         <int>749</int>
        </void>
       </void>
       <void class="java.awt.Point" method="getField">
        <string>y</string>
        <void method="set">
         <object idref="Point100"/>
         <int>751</int>
        </void>
       </void>
      </void>
      <void id="Point101" index="1">
       <void class="java.awt.Point" method="getField">
        <string>x</string>
        <void method="set">
         <object idref="Point101"/>
         <int>757</int>
        </void>
       </void>
       <void class="java.awt.Point" method="getField">
        <string>y</string>
        <void method="set">
         <object idref="Point101"/>
         <int>759</int>
        </void>
       </void>
      </void>
     </void>
     <void property="points">
      <object idref="PointArray52"/>
     </void>
     <void property="strokeWidth">
      <float>1.0</float>
     </void>
    </object>
   </void>
   <void method="add">
    <object class="net.sf.jaxodraw.object.text.JaxoLatexText" id="JaxoLatexText10">
     <void property="allign">
      <int>2</int>
     </void>
     <void property="color">
      <object idref="Color0"/>
     </void>
     <void property="latexTextSize">
      <int>9</int>
     </void>
     <void id="PointArray53" property="points">
      <void id="Point102" index="0">
       <void class="java.awt.Point" method="getField">
        <string>x</string>
        <void method="set">
         <object idref="Point102"/>
         <int>408</int>
        </void>
       </void>
       <void class="java.awt.Point" method="getField">
        <string>y</string>
        <void method="set">
         <object idref="Point102"/>
         <int>987</int>
        </void>
       </void>
      </void>
     </void>
     <void property="points">
      <object idref="PointArray53"/>
     </void>
     <void property="textString">
      <string>\gamma_1^{4d}</string>
     </void>
    </object>
   </void>
   <void method="add">
    <object class="net.sf.jaxodraw.object.group.JaxoGroup" id="JaxoGroup1">
     <void property="objectList">
      <void method="add">
       <object class="net.sf.jaxodraw.object.line.JaxoFLine" id="JaxoFLine24">
        <void property="DLSeparation">
         <float>2.0</float>
        </void>
        <void property="amp">
         <int>15</int>
        </void>
        <void property="arrowPosition">
         <float>0.5</float>
        </void>
        <void property="color">
         <object idref="Color2"/>
        </void>
        <void property="paintArrow">
         <boolean>true</boolean>
        </void>
        <void id="PointArray54" property="points">
         <void id="Point103" index="0">
          <void class="java.awt.Point" method="getField">
           <string>x</string>
           <void method="set">
            <object idref="Point103"/>
            <int>375</int>
           </void>
          </void>
          <void class="java.awt.Point" method="getField">
           <string>y</string>
           <void method="set">
            <object idref="Point103"/>
            <int>1081</int>
           </void>
          </void>
         </void>
         <void id="Point104" index="1">
          <void class="java.awt.Point" method="getField">
           <string>x</string>
           <void method="set">
            <object idref="Point104"/>
            <int>392</int>
           </void>
          </void>
          <void class="java.awt.Point" method="getField">
           <string>y</string>
           <void method="set">
            <object idref="Point104"/>
            <int>1039</int>
           </void>
          </void>
         </void>
        </void>
        <void property="points">
         <object idref="PointArray54"/>
        </void>
        <void property="strokeWidth">
         <float>1.0</float>
        </void>
       </object>
      </void>
      <void method="add">
       <object class="net.sf.jaxodraw.object.line.JaxoFLine" id="JaxoFLine25">
        <void property="DLSeparation">
         <float>2.0</float>
        </void>
        <void property="amp">
         <int>15</int>
        </void>
        <void property="arrowPosition">
         <float>0.5</float>
        </void>
        <void property="color">
         <object idref="Color2"/>
        </void>
        <void property="paintArrow">
         <boolean>true</boolean>
        </void>
        <void id="PointArray55" property="points">
         <void id="Point105" index="0">
          <void class="java.awt.Point" method="getField">
           <string>x</string>
           <void method="set">
            <object idref="Point105"/>
            <int>471</int>
           </void>
          </void>
          <void class="java.awt.Point" method="getField">
           <string>y</string>
           <void method="set">
            <object idref="Point105"/>
            <int>1080</int>
           </void>
          </void>
         </void>
         <void id="Point106" index="1">
          <void class="java.awt.Point" method="getField">
           <string>x</string>
           <void method="set">
            <object idref="Point106"/>
            <int>456</int>
           </void>
          </void>
          <void class="java.awt.Point" method="getField">
           <string>y</string>
           <void method="set">
            <object idref="Point106"/>
            <int>1036</int>
           </void>
          </void>
         </void>
        </void>
        <void property="points">
         <object idref="PointArray55"/>
        </void>
        <void property="strokeWidth">
         <float>1.0</float>
        </void>
       </object>
      </void>
      <void method="add">
       <object class="net.sf.jaxodraw.object.arc.JaxoFArc" id="JaxoFArc6">
        <void property="DLSeparation">
         <float>2.0</float>
        </void>
        <void property="amp">
         <int>15</int>
        </void>
        <void property="arrowPosition">
         <float>0.5</float>
        </void>
        <void property="color">
         <object idref="Color2"/>
        </void>
        <void property="paintArrow">
         <boolean>true</boolean>
        </void>
        <void id="PointArray56" property="points">
         <void id="Point107" index="0">
          <void class="java.awt.Point" method="getField">
           <string>x</string>
           <void method="set">
            <object idref="Point107"/>
            <int>393</int>
           </void>
          </void>
          <void class="java.awt.Point" method="getField">
           <string>y</string>
           <void method="set">
            <object idref="Point107"/>
            <int>1041</int>
           </void>
          </void>
         </void>
         <void id="Point108" index="1">
          <void class="java.awt.Point" method="getField">
           <string>x</string>
           <void method="set">
            <object idref="Point108"/>
            <int>363</int>
           </void>
          </void>
          <void class="java.awt.Point" method="getField">
           <string>y</string>
           <void method="set">
            <object idref="Point108"/>
            <int>986</int>
           </void>
          </void>
         </void>
         <void id="Point109" index="2">
          <void class="java.awt.Point" method="getField">
           <string>x</string>
           <void method="set">
            <object idref="Point109"/>
            <int>389</int>
           </void>
          </void>
          <void class="java.awt.Point" method="getField">
           <string>y</string>
           <void method="set">
            <object idref="Point109"/>
            <int>920</int>
           </void>
          </void>
         </void>
        </void>
        <void property="points">
         <object idref="PointArray56"/>
        </void>
        <void property="strokeWidth">
         <float>1.0</float>
        </void>
       </object>
      </void>
      <void method="add">
       <object class="net.sf.jaxodraw.object.arc.JaxoFArc" id="JaxoFArc7">
        <void property="DLSeparation">
         <float>2.0</float>
        </void>
        <void property="amp">
         <int>15</int>
        </void>
        <void property="arrowPosition">
         <float>0.5</float>
        </void>
        <void property="color">
         <object idref="Color2"/>
        </void>
        <void property="paintArrow">
         <boolean>true</boolean>
        </void>
        <void id="PointArray57" property="points">
         <void id="Point110" index="0">
          <void class="java.awt.Point" method="getField">
           <string>x</string>
           <void method="set">
            <object idref="Point110"/>
            <int>456</int>
           </void>
          </void>
          <void class="java.awt.Point" method="getField">
           <string>y</string>
           <void method="set">
            <object idref="Point110"/>
            <int>1038</int>
           </void>
          </void>
         </void>
         <void id="Point111" index="1">
          <void class="java.awt.Point" method="getField">
           <string>x</string>
           <void method="set">
            <object idref="Point111"/>
            <int>485</int>
           </void>
          </void>
          <void class="java.awt.Point" method="getField">
           <string>y</string>
           <void method="set">
            <object idref="Point111"/>
            <int>985</int>
           </void>
          </void>
         </void>
         <void id="Point112" index="2">
          <void class="java.awt.Point" method="getField">
           <string>x</string>
           <void method="set">
            <object idref="Point112"/>
            <int>457</int>
           </void>
          </void>
          <void class="java.awt.Point" method="getField">
           <string>y</string>
           <void method="set">
            <object idref="Point112"/>
            <int>918</int>
           </void>
          </void>
         </void>
        </void>
        <void property="points">
         <object idref="PointArray57"/>
        </void>
        <void property="strokeWidth">
         <float>1.0</float>
        </void>
       </object>
      </void>
      <void method="add">
       <object class="net.sf.jaxodraw.object.line.JaxoFLine" id="JaxoFLine26">
        <void property="DLSeparation">
         <float>2.0</float>
        </void>
        <void property="amp">
         <int>15</int>
        </void>
        <void property="arrowPosition">
         <float>0.5</float>
        </void>
        <void property="color">
         <object idref="Color2"/>
        </void>
        <void property="paintArrow">
         <boolean>true</boolean>
        </void>
        <void id="PointArray58" property="points">
         <void id="Point113" index="0">
          <void class="java.awt.Point" method="getField">
           <string>x</string>
           <void method="set">
            <object idref="Point113"/>
            <int>458</int>
           </void>
          </void>
          <void class="java.awt.Point" method="getField">
           <string>y</string>
           <void method="set">
            <object idref="Point113"/>
            <int>917</int>
           </void>
          </void>
         </void>
         <void id="Point114" index="1">
          <void class="java.awt.Point" method="getField">
           <string>x</string>
           <void method="set">
            <object idref="Point114"/>
            <int>476</int>
           </void>
          </void>
          <void class="java.awt.Point" method="getField">
           <string>y</string>
           <void method="set">
            <object idref="Point114"/>
            <int>884</int>
           </void>
          </void>
         </void>
        </void>
        <void property="points">
         <object idref="PointArray58"/>
        </void>
        <void property="strokeWidth">
         <float>1.0</float>
        </void>
       </object>
      </void>
      <void method="add">
       <object class="net.sf.jaxodraw.object.line.JaxoFLine" id="JaxoFLine27">
        <void property="DLSeparation">
         <float>2.0</float>
        </void>
        <void property="amp">
         <int>15</int>
        </void>
        <void property="arrowPosition">
         <float>0.5</float>
        </void>
        <void property="color">
         <object idref="Color2"/>
        </void>
        <void property="paintArrow">
         <boolean>true</boolean>
        </void>
        <void id="PointArray59" property="points">
         <void id="Point115" index="0">
          <void class="java.awt.Point" method="getField">
           <string>x</string>
           <void method="set">
            <object idref="Point115"/>
            <int>389</int>
           </void>
          </void>
          <void class="java.awt.Point" method="getField">
           <string>y</string>
           <void method="set">
            <object idref="Point115"/>
            <int>920</int>
           </void>
          </void>
         </void>
         <void id="Point116" index="1">
          <void class="java.awt.Point" method="getField">
           <string>x</string>
           <void method="set">
            <object idref="Point116"/>
            <int>372</int>
           </void>
          </void>
          <void class="java.awt.Point" method="getField">
           <string>y</string>
           <void method="set">
            <object idref="Point116"/>
            <int>882</int>
           </void>
          </void>
         </void>
        </void>
        <void property="points">
         <object idref="PointArray59"/>
        </void>
        <void property="strokeWidth">
         <float>1.0</float>
        </void>
       </object>
      </void>
      <void method="add">
       <object class="net.sf.jaxodraw.object.line.JaxoPLine" id="JaxoPLine9">
        <void property="DLSeparation">
         <float>2.0</float>
        </void>
        <void property="amp">
         <int>10</int>
        </void>
        <void property="color">
         <object idref="Color2"/>
        </void>
        <void id="PointArray60" property="points">
         <void id="Point117" index="0">
          <void class="java.awt.Point" method="getField">
           <string>x</string>
           <void method="set">
            <object idref="Point117"/>
            <int>389</int>
           </void>
          </void>
          <void class="java.awt.Point" method="getField">
           <string>y</string>
           <void method="set">
            <object idref="Point117"/>
            <int>920</int>
           </void>
          </void>
         </void>
         <void id="Point118" index="1">
          <void class="java.awt.Point" method="getField">
           <string>x</string>
           <void method="set">
            <object idref="Point118"/>
            <int>458</int>
           </void>
          </void>
          <void class="java.awt.Point" method="getField">
           <string>y</string>
           <void method="set">
            <object idref="Point118"/>
            <int>917</int>
           </void>
          </void>
         </void>
        </void>
        <void property="points">
         <object idref="PointArray60"/>
        </void>
        <void property="strokeWidth">
         <float>1.0</float>
        </void>
        <void property="wiggles">
         <int>4</int>
        </void>
       </object>
      </void>
      <void method="add">
       <object class="net.sf.jaxodraw.object.line.JaxoPLine" id="JaxoPLine10">
        <void property="DLSeparation">
         <float>2.0</float>
        </void>
        <void property="amp">
         <int>10</int>
        </void>
        <void property="color">
         <object idref="Color2"/>
        </void>
        <void id="PointArray61" property="points">
         <void id="Point119" index="0">
          <void class="java.awt.Point" method="getField">
           <string>x</string>
           <void method="set">
            <object idref="Point119"/>
            <int>392</int>
           </void>
          </void>
          <void class="java.awt.Point" method="getField">
           <string>y</string>
           <void method="set">
            <object idref="Point119"/>
            <int>1039</int>
           </void>
          </void>
         </void>
         <void id="Point120" index="1">
          <void class="java.awt.Point" method="getField">
           <string>x</string>
           <void method="set">
            <object idref="Point120"/>
            <int>458</int>
           </void>
          </void>
          <void class="java.awt.Point" method="getField">
           <string>y</string>
           <void method="set">
            <object idref="Point120"/>
            <int>1036</int>
           </void>
          </void>
         </void>
        </void>
        <void property="points">
         <object idref="PointArray61"/>
        </void>
        <void property="strokeWidth">
         <float>1.0</float>
        </void>
        <void property="wiggles">
         <int>4</int>
        </void>
       </object>
      </void>
     </void>
     <void id="PointArray62" property="points">
      <void id="Point121" index="0">
       <void class="java.awt.Point" method="getField">
        <string>x</string>
        <void method="set">
         <object idref="Point121"/>
         <int>359</int>
        </void>
       </void>
       <void class="java.awt.Point" method="getField">
        <string>y</string>
        <void method="set">
         <object idref="Point121"/>
         <int>881</int>
        </void>
       </void>
      </void>
      <void id="Point122" index="1">
       <void class="java.awt.Point" method="getField">
        <string>x</string>
        <void method="set">
         <object idref="Point122"/>
         <int>489</int>
        </void>
       </void>
       <void class="java.awt.Point" method="getField">
        <string>y</string>
        <void method="set">
         <object idref="Point122"/>
         <int>1082</int>
        </void>
       </void>
      </void>
     </void>
     <void property="points">
      <object idref="PointArray62"/>
     </void>
    </object>
   </void>
  </void>
 </object>
</java>
