<?xml version="1.0" encoding="UTF-8"?>
<java version="1.8.0_321" class="java.beans.XMLDecoder">
 <object class="net.sf.jaxodraw.graph.JaxoSaveGraph" id="JaxoSaveGraph0">
  <void property="jaxoDrawVersion">
   <string>2.1-0</string>
  </void>
  <void property="objectList">
   <void method="add">
    <object class="net.sf.jaxodraw.object.line.JaxoFLine" id="JaxoFLine0">
     <void property="DLSeparation">
      <float>2.0</float>
     </void>
     <void property="amp">
      <int>15</int>
     </void>
     <void property="arrowPosition">
      <float>0.5</float>
     </void>
     <void id="JaxoDefaultArrow0" property="arrow">
      <void id="Color0" property="color"/>
     </void>
     <void property="color">
      <object idref="Color0"/>
     </void>
     <void property="paintArrow">
      <boolean>true</boolean>
     </void>
     <void id="PointArray0" property="points">
      <void id="Point0" index="0">
       <void class="java.awt.Point" method="getField">
        <string>x</string>
        <void method="set">
         <object idref="Point0"/>
         <int>146</int>
        </void>
       </void>
       <void class="java.awt.Point" method="getField">
        <string>y</string>
        <void method="set">
         <object idref="Point0"/>
         <int>242</int>
        </void>
       </void>
      </void>
      <void id="Point1" index="1">
       <void class="java.awt.Point" method="getField">
        <string>x</string>
        <void method="set">
         <object idref="Point1"/>
         <int>175</int>
        </void>
       </void>
       <void class="java.awt.Point" method="getField">
        <string>y</string>
        <void method="set">
         <object idref="Point1"/>
         <int>178</int>
        </void>
       </void>
      </void>
     </void>
     <void property="points">
      <object idref="PointArray0"/>
     </void>
     <void property="strokeWidth">
      <float>1.0</float>
     </void>
    </object>
   </void>
   <void method="add">
    <object class="net.sf.jaxodraw.object.line.JaxoFLine" id="JaxoFLine1">
     <void property="DLSeparation">
      <float>2.0</float>
     </void>
     <void property="amp">
      <int>15</int>
     </void>
     <void property="arrowPosition">
      <float>0.5</float>
     </void>
     <void property="color">
      <object idref="Color0"/>
     </void>
     <void property="paintArrow">
      <boolean>true</boolean>
     </void>
     <void id="PointArray1" property="points">
      <void id="Point2" index="0">
       <void class="java.awt.Point" method="getField">
        <string>x</string>
        <void method="set">
         <object idref="Point2"/>
         <int>176</int>
        </void>
       </void>
       <void class="java.awt.Point" method="getField">
        <string>y</string>
        <void method="set">
         <object idref="Point2"/>
         <int>176</int>
        </void>
       </void>
      </void>
      <void id="Point3" index="1">
       <void class="java.awt.Point" method="getField">
        <string>x</string>
        <void method="set">
         <object idref="Point3"/>
         <int>144</int>
        </void>
       </void>
       <void class="java.awt.Point" method="getField">
        <string>y</string>
        <void method="set">
         <object idref="Point3"/>
         <int>114</int>
        </void>
       </void>
      </void>
     </void>
     <void property="points">
      <object idref="PointArray1"/>
     </void>
     <void property="strokeWidth">
      <float>1.0</float>
     </void>
    </object>
   </void>
   <void method="add">
    <object class="net.sf.jaxodraw.object.line.JaxoPLine" id="JaxoPLine0">
     <void property="DLSeparation">
      <float>2.0</float>
     </void>
     <void property="amp">
      <int>15</int>
     </void>
     <void property="color">
      <object idref="Color0"/>
     </void>
     <void id="PointArray2" property="points">
      <void id="Point4" index="0">
       <void class="java.awt.Point" method="getField">
        <string>x</string>
        <void method="set">
         <object idref="Point4"/>
         <int>175</int>
        </void>
       </void>
       <void class="java.awt.Point" method="getField">
        <string>y</string>
        <void method="set">
         <object idref="Point4"/>
         <int>176</int>
        </void>
       </void>
      </void>
      <void id="Point5" index="1">
       <void class="java.awt.Point" method="getField">
        <string>x</string>
        <void method="set">
         <object idref="Point5"/>
         <int>228</int>
        </void>
       </void>
       <void class="java.awt.Point" method="getField">
        <string>y</string>
        <void method="set">
         <object idref="Point5"/>
         <int>175</int>
        </void>
       </void>
      </void>
     </void>
     <void property="points">
      <object idref="PointArray2"/>
     </void>
     <void property="strokeWidth">
      <float>1.0</float>
     </void>
     <void property="wiggles">
      <int>3</int>
     </void>
    </object>
   </void>
   <void method="add">
    <object class="net.sf.jaxodraw.object.arc.JaxoFArc" id="JaxoFArc0">
     <void property="DLSeparation">
      <float>2.0</float>
     </void>
     <void property="amp">
      <int>15</int>
     </void>
     <void property="arrowPosition">
      <float>0.5</float>
     </void>
     <void property="color">
      <object idref="Color0"/>
     </void>
     <void property="paintArrow">
      <boolean>true</boolean>
     </void>
     <void id="PointArray3" property="points">
      <void id="Point6" index="0">
       <void class="java.awt.Point" method="getField">
        <string>x</string>
        <void method="set">
         <object idref="Point6"/>
         <int>229</int>
        </void>
       </void>
       <void class="java.awt.Point" method="getField">
        <string>y</string>
        <void method="set">
         <object idref="Point6"/>
         <int>176</int>
        </void>
       </void>
      </void>
      <void id="Point7" index="1">
       <void class="java.awt.Point" method="getField">
        <string>x</string>
        <void method="set">
         <object idref="Point7"/>
         <int>286</int>
        </void>
       </void>
       <void class="java.awt.Point" method="getField">
        <string>y</string>
        <void method="set">
         <object idref="Point7"/>
         <int>130</int>
        </void>
       </void>
      </void>
      <void id="Point8" index="2">
       <void class="java.awt.Point" method="getField">
        <string>x</string>
        <void method="set">
         <object idref="Point8"/>
         <int>340</int>
        </void>
       </void>
       <void class="java.awt.Point" method="getField">
        <string>y</string>
        <void method="set">
         <object idref="Point8"/>
         <int>178</int>
        </void>
       </void>
      </void>
     </void>
     <void property="points">
      <object idref="PointArray3"/>
     </void>
     <void property="strokeWidth">
      <float>1.0</float>
     </void>
    </object>
   </void>
   <void method="add">
    <object class="net.sf.jaxodraw.object.arc.JaxoFArc" id="JaxoFArc1">
     <void property="DLSeparation">
      <float>2.0</float>
     </void>
     <void property="amp">
      <int>15</int>
     </void>
     <void property="arrowPosition">
      <float>0.5</float>
     </void>
     <void property="color">
      <object idref="Color0"/>
     </void>
     <void property="paintArrow">
      <boolean>true</boolean>
     </void>
     <void id="PointArray4" property="points">
      <void id="Point9" index="0">
       <void class="java.awt.Point" method="getField">
        <string>x</string>
        <void method="set">
         <object idref="Point9"/>
         <int>340</int>
        </void>
       </void>
       <void class="java.awt.Point" method="getField">
        <string>y</string>
        <void method="set">
         <object idref="Point9"/>
         <int>178</int>
        </void>
       </void>
      </void>
      <void id="Point10" index="1">
       <void class="java.awt.Point" method="getField">
        <string>x</string>
        <void method="set">
         <object idref="Point10"/>
         <int>288</int>
        </void>
       </void>
       <void class="java.awt.Point" method="getField">
        <string>y</string>
        <void method="set">
         <object idref="Point10"/>
         <int>221</int>
        </void>
       </void>
      </void>
      <void id="Point11" index="2">
       <void class="java.awt.Point" method="getField">
        <string>x</string>
        <void method="set">
         <object idref="Point11"/>
         <int>229</int>
        </void>
       </void>
       <void class="java.awt.Point" method="getField">
        <string>y</string>
        <void method="set">
         <object idref="Point11"/>
         <int>177</int>
        </void>
       </void>
      </void>
     </void>
     <void property="points">
      <object idref="PointArray4"/>
     </void>
     <void property="strokeWidth">
      <float>1.0</float>
     </void>
    </object>
   </void>
   <void method="add">
    <object class="net.sf.jaxodraw.object.line.JaxoPLine" id="JaxoPLine1">
     <void property="DLSeparation">
      <float>2.0</float>
     </void>
     <void property="amp">
      <int>15</int>
     </void>
     <void property="color">
      <object idref="Color0"/>
     </void>
     <void id="PointArray5" property="points">
      <void id="Point12" index="0">
       <void class="java.awt.Point" method="getField">
        <string>x</string>
        <void method="set">
         <object idref="Point12"/>
         <int>340</int>
        </void>
       </void>
       <void class="java.awt.Point" method="getField">
        <string>y</string>
        <void method="set">
         <object idref="Point12"/>
         <int>177</int>
        </void>
       </void>
      </void>
      <void id="Point13" index="1">
       <void class="java.awt.Point" method="getField">
        <string>x</string>
        <void method="set">
         <object idref="Point13"/>
         <int>397</int>
        </void>
       </void>
       <void class="java.awt.Point" method="getField">
        <string>y</string>
        <void method="set">
         <object idref="Point13"/>
         <int>175</int>
        </void>
       </void>
      </void>
     </void>
     <void property="points">
      <object idref="PointArray5"/>
     </void>
     <void property="strokeWidth">
      <float>1.0</float>
     </void>
     <void property="wiggles">
      <int>3</int>
     </void>
    </object>
   </void>
   <void method="add">
    <object class="net.sf.jaxodraw.object.line.JaxoFLine" id="JaxoFLine2">
     <void property="DLSeparation">
      <float>2.0</float>
     </void>
     <void property="amp">
      <int>15</int>
     </void>
     <void property="arrowPosition">
      <float>0.5</float>
     </void>
     <void property="color">
      <object idref="Color0"/>
     </void>
     <void property="paintArrow">
      <boolean>true</boolean>
     </void>
     <void id="PointArray6" property="points">
      <void id="Point14" index="0">
       <void class="java.awt.Point" method="getField">
        <string>x</string>
        <void method="set">
         <object idref="Point14"/>
         <int>433</int>
        </void>
       </void>
       <void class="java.awt.Point" method="getField">
        <string>y</string>
        <void method="set">
         <object idref="Point14"/>
         <int>242</int>
        </void>
       </void>
      </void>
      <void id="Point15" index="1">
       <void class="java.awt.Point" method="getField">
        <string>x</string>
        <void method="set">
         <object idref="Point15"/>
         <int>399</int>
        </void>
       </void>
       <void class="java.awt.Point" method="getField">
        <string>y</string>
        <void method="set">
         <object idref="Point15"/>
         <int>175</int>
        </void>
       </void>
      </void>
     </void>
     <void property="points">
      <object idref="PointArray6"/>
     </void>
     <void property="strokeWidth">
      <float>1.0</float>
     </void>
    </object>
   </void>
   <void method="add">
    <object class="net.sf.jaxodraw.object.line.JaxoFLine" id="JaxoFLine3">
     <void property="DLSeparation">
      <float>2.0</float>
     </void>
     <void property="amp">
      <int>15</int>
     </void>
     <void property="arrowPosition">
      <float>0.5</float>
     </void>
     <void property="color">
      <object idref="Color0"/>
     </void>
     <void property="paintArrow">
      <boolean>true</boolean>
     </void>
     <void id="PointArray7" property="points">
      <void id="Point16" index="0">
       <void class="java.awt.Point" method="getField">
        <string>x</string>
        <void method="set">
         <object idref="Point16"/>
         <int>399</int>
        </void>
       </void>
       <void class="java.awt.Point" method="getField">
        <string>y</string>
        <void method="set">
         <object idref="Point16"/>
         <int>176</int>
        </void>
       </void>
      </void>
      <void id="Point17" index="1">
       <void class="java.awt.Point" method="getField">
        <string>x</string>
        <void method="set">
         <object idref="Point17"/>
         <int>433</int>
        </void>
       </void>
       <void class="java.awt.Point" method="getField">
        <string>y</string>
        <void method="set">
         <object idref="Point17"/>
         <int>113</int>
        </void>
       </void>
      </void>
     </void>
     <void property="points">
      <object idref="PointArray7"/>
     </void>
     <void property="strokeWidth">
      <float>1.0</float>
     </void>
    </object>
   </void>
   <void method="add">
    <object class="net.sf.jaxodraw.object.line.JaxoFLine" id="JaxoFLine4">
     <void property="DLSeparation">
      <float>2.0</float>
     </void>
     <void property="amp">
      <int>15</int>
     </void>
     <void property="arrowPosition">
      <float>0.5</float>
     </void>
     <void property="color">
      <object idref="Color0"/>
     </void>
     <void property="paintArrow">
      <boolean>true</boolean>
     </void>
     <void id="PointArray8" property="points">
      <void id="Point18" index="0">
       <void class="java.awt.Point" method="getField">
        <string>x</string>
        <void method="set">
         <object idref="Point18"/>
         <int>497</int>
        </void>
       </void>
       <void class="java.awt.Point" method="getField">
        <string>y</string>
        <void method="set">
         <object idref="Point18"/>
         <int>242</int>
        </void>
       </void>
      </void>
      <void id="Point19" index="1">
       <void class="java.awt.Point" method="getField">
        <string>x</string>
        <void method="set">
         <object idref="Point19"/>
         <int>528</int>
        </void>
       </void>
       <void class="java.awt.Point" method="getField">
        <string>y</string>
        <void method="set">
         <object idref="Point19"/>
         <int>176</int>
        </void>
       </void>
      </void>
     </void>
     <void property="points">
      <object idref="PointArray8"/>
     </void>
     <void property="strokeWidth">
      <float>1.0</float>
     </void>
    </object>
   </void>
   <void method="add">
    <object class="net.sf.jaxodraw.object.line.JaxoFLine" id="JaxoFLine5">
     <void property="DLSeparation">
      <float>2.0</float>
     </void>
     <void property="amp">
      <int>15</int>
     </void>
     <void property="arrowPosition">
      <float>0.5</float>
     </void>
     <void property="color">
      <object idref="Color0"/>
     </void>
     <void property="paintArrow">
      <boolean>true</boolean>
     </void>
     <void id="PointArray9" property="points">
      <void id="Point20" index="0">
       <void class="java.awt.Point" method="getField">
        <string>x</string>
        <void method="set">
         <object idref="Point20"/>
         <int>528</int>
        </void>
       </void>
       <void class="java.awt.Point" method="getField">
        <string>y</string>
        <void method="set">
         <object idref="Point20"/>
         <int>176</int>
        </void>
       </void>
      </void>
      <void id="Point21" index="1">
       <void class="java.awt.Point" method="getField">
        <string>x</string>
        <void method="set">
         <object idref="Point21"/>
         <int>497</int>
        </void>
       </void>
       <void class="java.awt.Point" method="getField">
        <string>y</string>
        <void method="set">
         <object idref="Point21"/>
         <int>113</int>
        </void>
       </void>
      </void>
     </void>
     <void property="points">
      <object idref="PointArray9"/>
     </void>
     <void property="strokeWidth">
      <float>1.0</float>
     </void>
    </object>
   </void>
   <void method="add">
    <object class="net.sf.jaxodraw.object.line.JaxoPLine" id="JaxoPLine2">
     <void property="DLSeparation">
      <float>2.0</float>
     </void>
     <void property="amp">
      <int>15</int>
     </void>
     <void property="color">
      <object idref="Color0"/>
     </void>
     <void id="PointArray10" property="points">
      <void id="Point22" index="0">
       <void class="java.awt.Point" method="getField">
        <string>x</string>
        <void method="set">
         <object idref="Point22"/>
         <int>529</int>
        </void>
       </void>
       <void class="java.awt.Point" method="getField">
        <string>y</string>
        <void method="set">
         <object idref="Point22"/>
         <int>176</int>
        </void>
       </void>
      </void>
      <void id="Point23" index="1">
       <void class="java.awt.Point" method="getField">
        <string>x</string>
        <void method="set">
         <object idref="Point23"/>
         <int>640</int>
        </void>
       </void>
       <void class="java.awt.Point" method="getField">
        <string>y</string>
        <void method="set">
         <object idref="Point23"/>
         <int>175</int>
        </void>
       </void>
      </void>
     </void>
     <void property="points">
      <object idref="PointArray10"/>
     </void>
     <void property="strokeWidth">
      <float>1.0</float>
     </void>
     <void property="wiggles">
      <int>6</int>
     </void>
    </object>
   </void>
   <void method="add">
    <object class="net.sf.jaxodraw.object.line.JaxoFLine" id="JaxoFLine6">
     <void property="DLSeparation">
      <float>2.0</float>
     </void>
     <void property="amp">
      <int>15</int>
     </void>
     <void property="arrowPosition">
      <float>0.5</float>
     </void>
     <void property="color">
      <object idref="Color0"/>
     </void>
     <void property="paintArrow">
      <boolean>true</boolean>
     </void>
     <void id="PointArray11" property="points">
      <void id="Point24" index="0">
       <void class="java.awt.Point" method="getField">
        <string>x</string>
        <void method="set">
         <object idref="Point24"/>
         <int>671</int>
        </void>
       </void>
       <void class="java.awt.Point" method="getField">
        <string>y</string>
        <void method="set">
         <object idref="Point24"/>
         <int>240</int>
        </void>
       </void>
      </void>
      <void id="Point25" index="1">
       <void class="java.awt.Point" method="getField">
        <string>x</string>
        <void method="set">
         <object idref="Point25"/>
         <int>641</int>
        </void>
       </void>
       <void class="java.awt.Point" method="getField">
        <string>y</string>
        <void method="set">
         <object idref="Point25"/>
         <int>174</int>
        </void>
       </void>
      </void>
     </void>
     <void property="points">
      <object idref="PointArray11"/>
     </void>
     <void property="strokeWidth">
      <float>1.0</float>
     </void>
    </object>
   </void>
   <void method="add">
    <object class="net.sf.jaxodraw.object.line.JaxoFLine" id="JaxoFLine7">
     <void property="DLSeparation">
      <float>2.0</float>
     </void>
     <void property="amp">
      <int>15</int>
     </void>
     <void property="arrowPosition">
      <float>0.5</float>
     </void>
     <void property="color">
      <object idref="Color0"/>
     </void>
     <void property="paintArrow">
      <boolean>true</boolean>
     </void>
     <void id="PointArray12" property="points">
      <void id="Point26" index="0">
       <void class="java.awt.Point" method="getField">
        <string>x</string>
        <void method="set">
         <object idref="Point26"/>
         <int>642</int>
        </void>
       </void>
       <void class="java.awt.Point" method="getField">
        <string>y</string>
        <void method="set">
         <object idref="Point26"/>
         <int>174</int>
        </void>
       </void>
      </void>
      <void id="Point27" index="1">
       <void class="java.awt.Point" method="getField">
        <string>x</string>
        <void method="set">
         <object idref="Point27"/>
         <int>673</int>
        </void>
       </void>
       <void class="java.awt.Point" method="getField">
        <string>y</string>
        <void method="set">
         <object idref="Point27"/>
         <int>111</int>
        </void>
       </void>
      </void>
     </void>
     <void property="points">
      <object idref="PointArray12"/>
     </void>
     <void property="strokeWidth">
      <float>1.0</float>
     </void>
    </object>
   </void>
   <void method="add">
    <object class="net.sf.jaxodraw.object.vertex.JaxoVertexT2" id="JaxoVertexT20">
     <void property="color">
      <object idref="Color0"/>
     </void>
     <void property="fillColor">
      <object class="java.awt.Color">
       <int>255</int>
       <int>255</int>
       <int>255</int>
       <int>255</int>
      </object>
     </void>
     <void id="PointArray13" property="points">
      <void id="Point28" index="0">
       <void class="java.awt.Point" method="getField">
        <string>x</string>
        <void method="set">
         <object idref="Point28"/>
         <int>583</int>
        </void>
       </void>
       <void class="java.awt.Point" method="getField">
        <string>y</string>
        <void method="set">
         <object idref="Point28"/>
         <int>176</int>
        </void>
       </void>
      </void>
      <void id="Point29" index="1">
       <void class="java.awt.Point" method="getField">
        <string>x</string>
        <void method="set">
         <object idref="Point29"/>
         <int>591</int>
        </void>
       </void>
       <void class="java.awt.Point" method="getField">
        <string>y</string>
        <void method="set">
         <object idref="Point29"/>
         <int>184</int>
        </void>
       </void>
      </void>
     </void>
     <void property="points">
      <object idref="PointArray13"/>
     </void>
     <void property="strokeWidth">
      <float>1.0</float>
     </void>
    </object>
   </void>
   <void method="add">
    <object class="net.sf.jaxodraw.object.text.JaxoLatexText" id="JaxoLatexText0">
     <void property="allign">
      <int>2</int>
     </void>
     <void property="color">
      <object idref="Color0"/>
     </void>
     <void property="latexTextSize">
      <int>9</int>
     </void>
     <void id="PointArray14" property="points">
      <void id="Point30" index="0">
       <void class="java.awt.Point" method="getField">
        <string>x</string>
        <void method="set">
         <object idref="Point30"/>
         <int>448</int>
        </void>
       </void>
       <void class="java.awt.Point" method="getField">
        <string>y</string>
        <void method="set">
         <object idref="Point30"/>
         <int>179</int>
        </void>
       </void>
      </void>
     </void>
     <void property="points">
      <object idref="PointArray14"/>
     </void>
     <void property="textString">
      <string>+</string>
     </void>
    </object>
   </void>
   <void method="add">
    <object class="net.sf.jaxodraw.object.text.JaxoLatexText" id="JaxoLatexText1">
     <void property="allign">
      <int>2</int>
     </void>
     <void property="color">
      <object idref="Color0"/>
     </void>
     <void property="latexTextSize">
      <int>9</int>
     </void>
     <void id="PointArray15" property="points">
      <void id="Point31" index="0">
       <void class="java.awt.Point" method="getField">
        <string>x</string>
        <void method="set">
         <object idref="Point31"/>
         <int>272</int>
        </void>
       </void>
       <void class="java.awt.Point" method="getField">
        <string>y</string>
        <void method="set">
         <object idref="Point31"/>
         <int>112</int>
        </void>
       </void>
      </void>
     </void>
     <void property="points">
      <object idref="PointArray15"/>
     </void>
     <void property="textString">
      <string>\gamma_1^1</string>
     </void>
    </object>
   </void>
   <void method="add">
    <object class="net.sf.jaxodraw.object.text.JaxoLatexText" id="JaxoLatexText2">
     <void property="allign">
      <int>2</int>
     </void>
     <void property="color">
      <object idref="Color0"/>
     </void>
     <void property="latexTextSize">
      <int>9</int>
     </void>
     <void id="PointArray16" property="points">
      <void id="Point32" index="0">
       <void class="java.awt.Point" method="getField">
        <string>x</string>
        <void method="set">
         <object idref="Point32"/>
         <int>544</int>
        </void>
       </void>
       <void class="java.awt.Point" method="getField">
        <string>y</string>
        <void method="set">
         <object idref="Point32"/>
         <int>128</int>
        </void>
       </void>
      </void>
     </void>
     <void property="points">
      <object idref="PointArray16"/>
     </void>
     <void property="textString">
      <string>R_q\Pi_0^* R_q</string>
     </void>
    </object>
   </void>
  </void>
 </object>
</java>
